Compiled from "CompletionProposalPopup.java"
class org.eclipse.jface.text.contentassist.CompletionProposalPopup implements org.eclipse.jface.text.contentassist.IContentAssistListener {
  org.eclipse.jface.text.ITextViewer fViewer;

  final org.eclipse.jface.text.contentassist.ContentAssistant fContentAssistant;

  private final org.eclipse.jface.text.contentassist.AdditionalInfoController fAdditionalInfoController;

  private final org.eclipse.jface.text.contentassist.PopupCloser fPopupCloser;

  org.eclipse.swt.widgets.Shell fProposalShell;

  private org.eclipse.swt.widgets.Table fProposalTable;

  private boolean fInserting;

  org.eclipse.jface.text.contentassist.CompletionProposalPopup$ProposalSelectionListener fKeyListener;

  private final java.util.List<org.eclipse.jface.text.DocumentEvent> fDocumentEvents;

  private org.eclipse.jface.text.IDocumentListener fDocumentListener;

  java.util.List<org.eclipse.jface.text.contentassist.ICompletionProposal> fFilteredProposals;

  java.util.List<org.eclipse.jface.text.contentassist.ICompletionProposal> fComputedProposals;

  int fInvocationOffset;

  int fFilterOffset;

  private org.eclipse.jface.text.contentassist.ICompletionProposal fLastProposal;

  org.eclipse.jface.contentassist.IContentAssistSubjectControl fContentAssistSubjectControl;

  final org.eclipse.jface.text.contentassist.ContentAssistSubjectControlAdapter fContentAssistSubjectControlAdapter;

  private org.eclipse.swt.graphics.Point fSize;

  private org.eclipse.jface.text.IEditingSupport fFocusHelper;

  private boolean fIsFilteredSubset;

  private final java.lang.Runnable fFilterRunnable;

  private final java.util.concurrent.atomic.AtomicBoolean fIsFilterPending;

  private org.eclipse.swt.widgets.Label fMessageText;

  private org.eclipse.swt.graphics.Font fMessageTextFont;

  int fLastCompletionOffset;

  private final org.eclipse.jface.text.contentassist.CompletionProposalPopup$EmptyProposal fEmptyProposal;

  private java.lang.String fEmptyMessage;

  private boolean fIsColoredLabelsSupportEnabled;

  org.eclipse.jface.text.contentassist.ICompletionProposalSorter fSorter;

  boolean fIsInitialSort;

  public org.eclipse.jface.text.contentassist.CompletionProposalPopup(org.eclipse.jface.text.contentassist.ContentAssistant, org.eclipse.jface.text.ITextViewer, org.eclipse.jface.text.contentassist.AdditionalInfoController);
    Code:
       0: aload_0
       1: invokespecial #66                 // Method java/lang/Object."<init>":()V
       4: aload_0
       5: new           #69                 // class org/eclipse/jface/text/contentassist/PopupCloser
       8: dup
       9: invokespecial #71                 // Method org/eclipse/jface/text/contentassist/PopupCloser."<init>":()V
      12: putfield      #72                 // Field fPopupCloser:Lorg/eclipse/jface/text/contentassist/PopupCloser;
      15: aload_0
      16: iconst_0
      17: putfield      #74                 // Field fInserting:Z
      20: aload_0
      21: new           #76                 // class java/util/ArrayList
      24: dup
      25: invokespecial #78                 // Method java/util/ArrayList."<init>":()V
      28: putfield      #79                 // Field fDocumentEvents:Ljava/util/List;
      31: aload_0
      32: new           #81                 // class org/eclipse/jface/text/contentassist/CompletionProposalPopup$1
      35: dup
      36: aload_0
      37: invokespecial #83                 // Method org/eclipse/jface/text/contentassist/CompletionProposalPopup$1."<init>":(Lorg/eclipse/jface/text/contentassist/CompletionProposalPopup;)V
      40: putfield      #86                 // Field fFilterRunnable:Ljava/lang/Runnable;
      43: aload_0
      44: new           #88                 // class java/util/concurrent/atomic/AtomicBoolean
      47: dup
      48: iconst_0
      49: invokespecial #90                 // Method java/util/concurrent/atomic/AtomicBoolean."<init>":(Z)V
      52: putfield      #93                 // Field fIsFilterPending:Ljava/util/concurrent/atomic/AtomicBoolean;
      55: aload_0
      56: new           #95                 // class org/eclipse/jface/text/contentassist/CompletionProposalPopup$EmptyProposal
      59: dup
      60: invokespecial #97                 // Method org/eclipse/jface/text/contentassist/CompletionProposalPopup$EmptyProposal."<init>":()V
      63: putfield      #98                 // Field fEmptyProposal:Lorg/eclipse/jface/text/contentassist/CompletionProposalPopup$EmptyProposal;
      66: aload_0
      67: aconst_null
      68: putfield      #100                // Field fEmptyMessage:Ljava/lang/String;
      71: aload_0
      72: iconst_0
      73: putfield      #102                // Field fIsColoredLabelsSupportEnabled:Z
      76: aload_0
      77: aload_1
      78: putfield      #104                // Field fContentAssistant:Lorg/eclipse/jface/text/contentassist/ContentAssistant;
      81: aload_0
      82: aload_2
      83: putfield      #106                // Field fViewer:Lorg/eclipse/jface/text/ITextViewer;
      86: aload_0
      87: aload_3
      88: putfield      #108                // Field fAdditionalInfoController:Lorg/eclipse/jface/text/contentassist/AdditionalInfoController;
      91: aload_0
      92: new           #110                // class org/eclipse/jface/text/contentassist/ContentAssistSubjectControlAdapter
      95: dup
      96: aload_0
      97: getfield      #106                // Field fViewer:Lorg/eclipse/jface/text/ITextViewer;
     100: invokespecial #112                // Method org/eclipse/jface/text/contentassist/ContentAssistSubjectControlAdapter."<init>":(Lorg/eclipse/jface/text/ITextViewer;)V
     103: putfield      #115                // Field fContentAssistSubjectControlAdapter:Lorg/eclipse/jface/text/contentassist/ContentAssistSubjectControlAdapter;
     106: return

  public org.eclipse.jface.text.contentassist.CompletionProposalPopup(org.eclipse.jface.text.contentassist.ContentAssistant, org.eclipse.jface.contentassist.IContentAssistSubjectControl, org.eclipse.jface.text.contentassist.AdditionalInfoController);
    Code:
       0: aload_0
       1: invokespecial #66                 // Method java/lang/Object."<init>":()V
       4: aload_0
       5: new           #69                 // class org/eclipse/jface/text/contentassist/PopupCloser
       8: dup
       9: invokespecial #71                 // Method org/eclipse/jface/text/contentassist/PopupCloser."<init>":()V
      12: putfield      #72                 // Field fPopupCloser:Lorg/eclipse/jface/text/contentassist/PopupCloser;
      15: aload_0
      16: iconst_0
      17: putfield      #74                 // Field fInserting:Z
      20: aload_0
      21: new           #76                 // class java/util/ArrayList
      24: dup
      25: invokespecial #78                 // Method java/util/ArrayList."<init>":()V
      28: putfield      #79                 // Field fDocumentEvents:Ljava/util/List;
      31: aload_0
      32: new           #81                 // class org/eclipse/jface/text/contentassist/CompletionProposalPopup$1
      35: dup
      36: aload_0
      37: invokespecial #83                 // Method org/eclipse/jface/text/contentassist/CompletionProposalPopup$1."<init>":(Lorg/eclipse/jface/text/contentassist/CompletionProposalPopup;)V
      40: putfield      #86                 // Field fFilterRunnable:Ljava/lang/Runnable;
      43: aload_0
      44: new           #88                 // class java/util/concurrent/atomic/AtomicBoolean
      47: dup
      48: iconst_0
      49: invokespecial #90                 // Method java/util/concurrent/atomic/AtomicBoolean."<init>":(Z)V
      52: putfield      #93                 // Field fIsFilterPending:Ljava/util/concurrent/atomic/AtomicBoolean;
      55: aload_0
      56: new           #95                 // class org/eclipse/jface/text/contentassist/CompletionProposalPopup$EmptyProposal
      59: dup
      60: invokespecial #97                 // Method org/eclipse/jface/text/contentassist/CompletionProposalPopup$EmptyProposal."<init>":()V
      63: putfield      #98                 // Field fEmptyProposal:Lorg/eclipse/jface/text/contentassist/CompletionProposalPopup$EmptyProposal;
      66: aload_0
      67: aconst_null
      68: putfield      #100                // Field fEmptyMessage:Ljava/lang/String;
      71: aload_0
      72: iconst_0
      73: putfield      #102                // Field fIsColoredLabelsSupportEnabled:Z
      76: aload_0
      77: aload_1
      78: putfield      #104                // Field fContentAssistant:Lorg/eclipse/jface/text/contentassist/ContentAssistant;
      81: aload_0
      82: aload_2
      83: putfield      #125                // Field fContentAssistSubjectControl:Lorg/eclipse/jface/contentassist/IContentAssistSubjectControl;
      86: aload_0
      87: aload_3
      88: putfield      #108                // Field fAdditionalInfoController:Lorg/eclipse/jface/text/contentassist/AdditionalInfoController;
      91: aload_0
      92: new           #110                // class org/eclipse/jface/text/contentassist/ContentAssistSubjectControlAdapter
      95: dup
      96: aload_0
      97: getfield      #125                // Field fContentAssistSubjectControl:Lorg/eclipse/jface/contentassist/IContentAssistSubjectControl;
     100: invokespecial #127                // Method org/eclipse/jface/text/contentassist/ContentAssistSubjectControlAdapter."<init>":(Lorg/eclipse/jface/contentassist/IContentAssistSubjectControl;)V
     103: putfield      #115                // Field fContentAssistSubjectControlAdapter:Lorg/eclipse/jface/text/contentassist/ContentAssistSubjectControlAdapter;
     106: return

  public java.lang.String showProposals(boolean);
    Code:
       0: aload_0
       1: getfield      #133                // Field fKeyListener:Lorg/eclipse/jface/text/contentassist/CompletionProposalPopup$ProposalSelectionListener;
       4: ifnonnull     19
       7: aload_0
       8: new           #135                // class org/eclipse/jface/text/contentassist/CompletionProposalPopup$ProposalSelectionListener
      11: dup
      12: aload_0
      13: invokespecial #137                // Method org/eclipse/jface/text/contentassist/CompletionProposalPopup$ProposalSelectionListener."<init>":(Lorg/eclipse/jface/text/contentassist/CompletionProposalPopup;)V
      16: putfield      #133                // Field fKeyListener:Lorg/eclipse/jface/text/contentassist/CompletionProposalPopup$ProposalSelectionListener;
      19: aload_0
      20: getfield      #115                // Field fContentAssistSubjectControlAdapter:Lorg/eclipse/jface/text/contentassist/ContentAssistSubjectControlAdapter;
      23: invokevirtual #138                // Method org/eclipse/jface/text/contentassist/ContentAssistSubjectControlAdapter.getControl:()Lorg/eclipse/swt/widgets/Control;
      26: astore_2
      27: aload_0
      28: getfield      #142                // Field fProposalShell:Lorg/eclipse/swt/widgets/Shell;
      31: invokestatic  #144                // Method org/eclipse/jface/util/Util.isValid:(Lorg/eclipse/swt/widgets/Widget;)Z
      34: ifne          76
      37: aload_2
      38: ifnull        76
      41: aload_2
      42: invokevirtual #150                // Method org/eclipse/swt/widgets/Control.isDisposed:()Z
      45: ifne          76
      48: aload_0
      49: getfield      #115                // Field fContentAssistSubjectControlAdapter:Lorg/eclipse/jface/text/contentassist/ContentAssistSubjectControlAdapter;
      52: aload_0
      53: getfield      #133                // Field fKeyListener:Lorg/eclipse/jface/text/contentassist/CompletionProposalPopup$ProposalSelectionListener;
      56: invokevirtual #156                // Method org/eclipse/jface/text/contentassist/ContentAssistSubjectControlAdapter.addKeyListener:(Lorg/eclipse/swt/events/KeyListener;)V
      59: aload_2
      60: invokevirtual #160                // Method org/eclipse/swt/widgets/Control.getDisplay:()Lorg/eclipse/swt/widgets/Display;
      63: aload_0
      64: iload_1
      65: invokedynamic #164,  0            // InvokeDynamic #0:run:(Lorg/eclipse/jface/text/contentassist/CompletionProposalPopup;Z)Ljava/lang/Runnable;
      70: invokestatic  #168                // Method org/eclipse/swt/custom/BusyIndicator.showWhile:(Lorg/eclipse/swt/widgets/Display;Ljava/lang/Runnable;)V
      73: goto          88
      76: aload_0
      77: aload_0
      78: getfield      #174                // Field fFilterOffset:I
      81: putfield      #176                // Field fLastCompletionOffset:I
      84: aload_0
      85: invokevirtual #178                // Method handleRepeatedInvocation:()V
      88: aload_0
      89: invokevirtual #181                // Method getErrorMessage:()Ljava/lang/String;
      92: areturn

  boolean hideWhenNoProposals(boolean);
    Code:
       0: iload_1
       1: ifne          14
       4: aload_0
       5: getfield      #104                // Field fContentAssistant:Lorg/eclipse/jface/text/contentassist/ContentAssistant;
       8: invokevirtual #191                // Method org/eclipse/jface/text/contentassist/ContentAssistant.isShowEmptyList:()Z
      11: ifne          50
      14: iload_1
      15: ifne          44
      18: aload_0
      19: getfield      #115                // Field fContentAssistSubjectControlAdapter:Lorg/eclipse/jface/text/contentassist/ContentAssistSubjectControlAdapter;
      22: invokevirtual #138                // Method org/eclipse/jface/text/contentassist/ContentAssistSubjectControlAdapter.getControl:()Lorg/eclipse/swt/widgets/Control;
      25: astore_2
      26: aload_2
      27: ifnull        44
      30: aload_2
      31: invokevirtual #150                // Method org/eclipse/swt/widgets/Control.isDisposed:()Z
      34: ifne          44
      37: aload_2
      38: invokevirtual #160                // Method org/eclipse/swt/widgets/Control.getDisplay:()Lorg/eclipse/swt/widgets/Display;
      41: invokevirtual #196                // Method org/eclipse/swt/widgets/Display.beep:()V
      44: aload_0
      45: invokevirtual #201                // Method hide:()V
      48: iconst_1
      49: ireturn
      50: iconst_0
      51: ireturn

  void handleRepeatedInvocation();
    Code:
       0: aload_0
       1: getfield      #104                // Field fContentAssistant:Lorg/eclipse/jface/text/contentassist/ContentAssistant;
       4: invokevirtual #204                // Method org/eclipse/jface/text/contentassist/ContentAssistant.isRepeatedInvocationMode:()Z
       7: ifeq          31
      10: aload_0
      11: aload_0
      12: aload_0
      13: getfield      #174                // Field fFilterOffset:I
      16: invokevirtual #207                // Method computeProposals:(I)Ljava/util/List;
      19: putfield      #211                // Field fComputedProposals:Ljava/util/List;
      22: aload_0
      23: aload_0
      24: getfield      #211                // Field fComputedProposals:Ljava/util/List;
      27: iconst_0
      28: invokevirtual #213                // Method setProposals:(Ljava/util/List;Z)V
      31: return

  java.util.List<org.eclipse.jface.text.contentassist.ICompletionProposal> computeProposals(int);
    Code:
       0: aload_0
       1: getfield      #125                // Field fContentAssistSubjectControl:Lorg/eclipse/jface/contentassist/IContentAssistSubjectControl;
       4: ifnull        23
       7: aload_0
       8: getfield      #104                // Field fContentAssistant:Lorg/eclipse/jface/text/contentassist/ContentAssistant;
      11: aload_0
      12: getfield      #125                // Field fContentAssistSubjectControl:Lorg/eclipse/jface/contentassist/IContentAssistSubjectControl;
      15: iload_1
      16: invokevirtual #218                // Method org/eclipse/jface/text/contentassist/ContentAssistant.computeCompletionProposals:(Lorg/eclipse/jface/contentassist/IContentAssistSubjectControl;I)[Lorg/eclipse/jface/text/contentassist/ICompletionProposal;
      19: astore_2
      20: goto          36
      23: aload_0
      24: getfield      #104                // Field fContentAssistant:Lorg/eclipse/jface/text/contentassist/ContentAssistant;
      27: aload_0
      28: getfield      #106                // Field fViewer:Lorg/eclipse/jface/text/ITextViewer;
      31: iload_1
      32: invokevirtual #222                // Method org/eclipse/jface/text/contentassist/ContentAssistant.computeCompletionProposals:(Lorg/eclipse/jface/text/ITextViewer;I)[Lorg/eclipse/jface/text/contentassist/ICompletionProposal;
      35: astore_2
      36: aload_2
      37: ifnonnull     44
      40: invokestatic  #225                // Method java/util/Collections.emptyList:()Ljava/util/List;
      43: areturn
      44: aload_2
      45: invokestatic  #231                // Method java/util/Arrays.asList:([Ljava/lang/Object;)Ljava/util/List;
      48: astore_3
      49: aload_0
      50: getfield      #237                // Field fSorter:Lorg/eclipse/jface/text/contentassist/ICompletionProposalSorter;
      53: ifnull        66
      56: aload_0
      57: aload_3
      58: invokevirtual #239                // Method sortProposals:(Ljava/util/List;)V
      61: aload_0
      62: iconst_1
      63: putfield      #243                // Field fIsInitialSort:Z
      66: aload_3
      67: areturn

  java.lang.String getErrorMessage();
    Code:
       0: aload_0
       1: getfield      #104                // Field fContentAssistant:Lorg/eclipse/jface/text/contentassist/ContentAssistant;
       4: invokevirtual #253                // Method org/eclipse/jface/text/contentassist/ContentAssistant.getErrorMessage:()Ljava/lang/String;
       7: areturn

  void createProposalSelector();
    Code:
       0: aload_0
       1: getfield      #142                // Field fProposalShell:Lorg/eclipse/swt/widgets/Shell;
       4: invokestatic  #144                // Method org/eclipse/jface/util/Util.isValid:(Lorg/eclipse/swt/widgets/Widget;)Z
       7: ifeq          11
      10: return
      11: aload_0
      12: getfield      #115                // Field fContentAssistSubjectControlAdapter:Lorg/eclipse/jface/text/contentassist/ContentAssistSubjectControlAdapter;
      15: invokevirtual #138                // Method org/eclipse/jface/text/contentassist/ContentAssistSubjectControlAdapter.getControl:()Lorg/eclipse/swt/widgets/Control;
      18: astore_1
      19: aload_0
      20: new           #255                // class org/eclipse/swt/widgets/Shell
      23: dup
      24: aload_1
      25: invokevirtual #257                // Method org/eclipse/swt/widgets/Control.getShell:()Lorg/eclipse/swt/widgets/Shell;
      28: sipush        16400
      31: invokespecial #261                // Method org/eclipse/swt/widgets/Shell."<init>":(Lorg/eclipse/swt/widgets/Shell;I)V
      34: putfield      #142                // Field fProposalShell:Lorg/eclipse/swt/widgets/Shell;
      37: aload_0
      38: getfield      #142                // Field fProposalShell:Lorg/eclipse/swt/widgets/Shell;
      41: invokestatic  #264                // Method org/eclipse/jface/resource/JFaceResources.getDefaultFont:()Lorg/eclipse/swt/graphics/Font;
      44: invokevirtual #270                // Method org/eclipse/swt/widgets/Shell.setFont:(Lorg/eclipse/swt/graphics/Font;)V
      47: aload_0
      48: new           #274                // class org/eclipse/swt/widgets/Table
      51: dup
      52: aload_0
      53: getfield      #142                // Field fProposalShell:Lorg/eclipse/swt/widgets/Shell;
      56: ldc_w         #276                // int 268436224
      59: invokespecial #277                // Method org/eclipse/swt/widgets/Table."<init>":(Lorg/eclipse/swt/widgets/Composite;I)V
      62: putfield      #280                // Field fProposalTable:Lorg/eclipse/swt/widgets/Table;
      65: aload_0
      66: invokedynamic #282,  0            // InvokeDynamic #1:handleEvent:(Lorg/eclipse/jface/text/contentassist/CompletionProposalPopup;)Lorg/eclipse/swt/widgets/Listener;
      71: astore_2
      72: aload_0
      73: getfield      #280                // Field fProposalTable:Lorg/eclipse/swt/widgets/Table;
      76: bipush        36
      78: aload_2
      79: invokevirtual #286                // Method org/eclipse/swt/widgets/Table.addListener:(ILorg/eclipse/swt/widgets/Listener;)V
      82: aload_0
      83: aload_0
      84: getfield      #104                // Field fContentAssistant:Lorg/eclipse/jface/text/contentassist/ContentAssistant;
      87: invokevirtual #290                // Method org/eclipse/jface/text/contentassist/ContentAssistant.isColoredLabelsSupportEnabled:()Z
      90: putfield      #102                // Field fIsColoredLabelsSupportEnabled:Z
      93: aload_0
      94: getfield      #102                // Field fIsColoredLabelsSupportEnabled:Z
      97: ifeq          107
     100: aload_0
     101: getfield      #280                // Field fProposalTable:Lorg/eclipse/swt/widgets/Table;
     104: invokestatic  #293                // Method org/eclipse/jface/internal/text/TableOwnerDrawSupport.install:(Lorg/eclipse/swt/widgets/Table;)V
     107: aload_0
     108: getfield      #280                // Field fProposalTable:Lorg/eclipse/swt/widgets/Table;
     111: iconst_0
     112: iconst_0
     113: invokevirtual #299                // Method org/eclipse/swt/widgets/Table.setLocation:(II)V
     116: aload_0
     117: getfield      #108                // Field fAdditionalInfoController:Lorg/eclipse/jface/text/contentassist/AdditionalInfoController;
     120: ifnull        136
     123: aload_0
     124: getfield      #108                // Field fAdditionalInfoController:Lorg/eclipse/jface/text/contentassist/AdditionalInfoController;
     127: bipush        50
     129: bipush        10
     131: iconst_1
     132: iconst_1
     133: invokevirtual #303                // Method org/eclipse/jface/text/contentassist/AdditionalInfoController.setSizeConstraints:(IIZZ)V
     136: new           #309                // class org/eclipse/swt/layout/GridLayout
     139: dup
     140: invokespecial #311                // Method org/eclipse/swt/layout/GridLayout."<init>":()V
     143: astore        4
     145: aload         4
     147: iconst_0
     148: putfield      #312                // Field org/eclipse/swt/layout/GridLayout.marginWidth:I
     151: aload         4
     153: iconst_0
     154: putfield      #315                // Field org/eclipse/swt/layout/GridLayout.marginHeight:I
     157: aload         4
     159: iconst_1
     160: putfield      #318                // Field org/eclipse/swt/layout/GridLayout.verticalSpacing:I
     163: aload_0
     164: getfield      #142                // Field fProposalShell:Lorg/eclipse/swt/widgets/Shell;
     167: aload         4
     169: invokevirtual #321                // Method org/eclipse/swt/widgets/Shell.setLayout:(Lorg/eclipse/swt/widgets/Layout;)V
     172: aload_0
     173: getfield      #104                // Field fContentAssistant:Lorg/eclipse/jface/text/contentassist/ContentAssistant;
     176: invokevirtual #325                // Method org/eclipse/jface/text/contentassist/ContentAssistant.isStatusLineVisible:()Z
     179: ifeq          186
     182: aload_0
     183: invokevirtual #328                // Method createMessageText:()V
     186: new           #331                // class org/eclipse/swt/layout/GridData
     189: dup
     190: sipush        1808
     193: invokespecial #333                // Method org/eclipse/swt/layout/GridData."<init>":(I)V
     196: astore        5
     198: aload_0
     199: getfield      #104                // Field fContentAssistant:Lorg/eclipse/jface/text/contentassist/ContentAssistant;
     202: invokevirtual #336                // Method org/eclipse/jface/text/contentassist/ContentAssistant.restoreCompletionProposalPopupSize:()Lorg/eclipse/swt/graphics/Point;
     205: astore        6
     207: aload         6
     209: ifnull        233
     212: aload_0
     213: getfield      #280                // Field fProposalTable:Lorg/eclipse/swt/widgets/Table;
     216: aload         5
     218: invokevirtual #340                // Method org/eclipse/swt/widgets/Table.setLayoutData:(Ljava/lang/Object;)V
     221: aload_0
     222: getfield      #142                // Field fProposalShell:Lorg/eclipse/swt/widgets/Shell;
     225: aload         6
     227: invokevirtual #344                // Method org/eclipse/swt/widgets/Shell.setSize:(Lorg/eclipse/swt/graphics/Point;)V
     230: goto          361
     233: aload_0
     234: getfield      #280                // Field fProposalTable:Lorg/eclipse/swt/widgets/Table;
     237: invokevirtual #348                // Method org/eclipse/swt/widgets/Table.getItemHeight:()I
     240: bipush        10
     242: imul
     243: istore        7
     245: ldc2_w        #352                // double 2.0d
     248: dstore        8
     250: iload         7
     252: i2d
     253: dload         8
     255: dmul
     256: d2i
     257: istore        10
     259: aload_0
     260: getfield      #142                // Field fProposalShell:Lorg/eclipse/swt/widgets/Shell;
     263: invokevirtual #354                // Method org/eclipse/swt/widgets/Shell.getDisplay:()Lorg/eclipse/swt/widgets/Display;
     266: aload_0
     267: invokevirtual #355                // Method getLocation:()Lorg/eclipse/swt/graphics/Point;
     270: invokestatic  #358                // Method org/eclipse/jface/util/Util.getClosestMonitor:(Lorg/eclipse/swt/widgets/Display;Lorg/eclipse/swt/graphics/Point;)Lorg/eclipse/swt/widgets/Monitor;
     273: astore        11
     275: aload         11
     277: invokevirtual #362                // Method org/eclipse/swt/widgets/Monitor.getClientArea:()Lorg/eclipse/swt/graphics/Rectangle;
     280: astore        12
     282: iload         10
     284: aload         12
     286: getfield      #368                // Field org/eclipse/swt/graphics/Rectangle.width:I
     289: iconst_4
     290: idiv
     291: invokestatic  #373                // Method java/lang/Math.min:(II)I
     294: istore        10
     296: iload         7
     298: aload         12
     300: getfield      #379                // Field org/eclipse/swt/graphics/Rectangle.height:I
     303: iconst_4
     304: idiv
     305: invokestatic  #373                // Method java/lang/Math.min:(II)I
     308: istore        7
     310: aload_0
     311: getfield      #280                // Field fProposalTable:Lorg/eclipse/swt/widgets/Table;
     314: iconst_0
     315: iconst_0
     316: iload         10
     318: iload         7
     320: invokevirtual #382                // Method org/eclipse/swt/widgets/Table.computeTrim:(IIII)Lorg/eclipse/swt/graphics/Rectangle;
     323: astore        13
     325: aload         5
     327: aload         13
     329: getfield      #379                // Field org/eclipse/swt/graphics/Rectangle.height:I
     332: putfield      #386                // Field org/eclipse/swt/layout/GridData.heightHint:I
     335: aload         5
     337: aload         13
     339: getfield      #368                // Field org/eclipse/swt/graphics/Rectangle.width:I
     342: putfield      #389                // Field org/eclipse/swt/layout/GridData.widthHint:I
     345: aload_0
     346: getfield      #280                // Field fProposalTable:Lorg/eclipse/swt/widgets/Table;
     349: aload         5
     351: invokevirtual #340                // Method org/eclipse/swt/widgets/Table.setLayoutData:(Ljava/lang/Object;)V
     354: aload_0
     355: getfield      #142                // Field fProposalShell:Lorg/eclipse/swt/widgets/Shell;
     358: invokevirtual #392                // Method org/eclipse/swt/widgets/Shell.pack:()V
     361: aload_0
     362: getfield      #104                // Field fContentAssistant:Lorg/eclipse/jface/text/contentassist/ContentAssistant;
     365: aload_0
     366: aload_0
     367: getfield      #142                // Field fProposalShell:Lorg/eclipse/swt/widgets/Shell;
     370: iconst_0
     371: aload_0
     372: getfield      #104                // Field fContentAssistant:Lorg/eclipse/jface/text/contentassist/ContentAssistant;
     375: invokevirtual #395                // Method org/eclipse/jface/text/contentassist/ContentAssistant.getSelectionOffset:()I
     378: invokevirtual #398                // Method org/eclipse/jface/text/contentassist/ContentAssistant.addToLayout:(Ljava/lang/Object;Lorg/eclipse/swt/widgets/Shell;II)V
     381: aload_0
     382: getfield      #142                // Field fProposalShell:Lorg/eclipse/swt/widgets/Shell;
     385: new           #402                // class org/eclipse/jface/text/contentassist/CompletionProposalPopup$2
     388: dup
     389: aload_0
     390: invokespecial #404                // Method org/eclipse/jface/text/contentassist/CompletionProposalPopup$2."<init>":(Lorg/eclipse/jface/text/contentassist/CompletionProposalPopup;)V
     393: invokevirtual #405                // Method org/eclipse/swt/widgets/Shell.addControlListener:(Lorg/eclipse/swt/events/ControlListener;)V
     396: aload_0
     397: aload_1
     398: invokevirtual #409                // Method getBackgroundColor:(Lorg/eclipse/swt/widgets/Control;)Lorg/eclipse/swt/graphics/Color;
     401: astore        7
     403: aload         7
     405: ifnonnull     416
     408: invokestatic  #413                // Method org/eclipse/swt/widgets/Display.getDefault:()Lorg/eclipse/swt/widgets/Display;
     411: invokestatic  #416                // Method org/eclipse/jface/resource/JFaceColors.getInformationViewerBackgroundColor:(Lorg/eclipse/swt/widgets/Display;)Lorg/eclipse/swt/graphics/Color;
     414: astore        7
     416: aload_0
     417: aload_1
     418: invokevirtual #422                // Method getForegroundColor:(Lorg/eclipse/swt/widgets/Control;)Lorg/eclipse/swt/graphics/Color;
     421: astore        8
     423: aload         8
     425: ifnonnull     436
     428: invokestatic  #413                // Method org/eclipse/swt/widgets/Display.getDefault:()Lorg/eclipse/swt/widgets/Display;
     431: invokestatic  #425                // Method org/eclipse/jface/resource/JFaceColors.getInformationViewerForegroundColor:(Lorg/eclipse/swt/widgets/Display;)Lorg/eclipse/swt/graphics/Color;
     434: astore        8
     436: aload_0
     437: getfield      #142                // Field fProposalShell:Lorg/eclipse/swt/widgets/Shell;
     440: aload         7
     442: invokevirtual #428                // Method org/eclipse/swt/widgets/Shell.setBackground:(Lorg/eclipse/swt/graphics/Color;)V
     445: aload_0
     446: getfield      #280                // Field fProposalTable:Lorg/eclipse/swt/widgets/Table;
     449: aload         7
     451: invokevirtual #432                // Method org/eclipse/swt/widgets/Table.setBackground:(Lorg/eclipse/swt/graphics/Color;)V
     454: aload_0
     455: getfield      #280                // Field fProposalTable:Lorg/eclipse/swt/widgets/Table;
     458: aload         8
     460: invokevirtual #433                // Method org/eclipse/swt/widgets/Table.setForeground:(Lorg/eclipse/swt/graphics/Color;)V
     463: aload_0
     464: getfield      #280                // Field fProposalTable:Lorg/eclipse/swt/widgets/Table;
     467: new           #436                // class org/eclipse/jface/text/contentassist/CompletionProposalPopup$3
     470: dup
     471: aload_0
     472: invokespecial #438                // Method org/eclipse/jface/text/contentassist/CompletionProposalPopup$3."<init>":(Lorg/eclipse/jface/text/contentassist/CompletionProposalPopup;)V
     475: invokevirtual #439                // Method org/eclipse/swt/widgets/Table.addSelectionListener:(Lorg/eclipse/swt/events/SelectionListener;)V
     478: aload_0
     479: getfield      #72                 // Field fPopupCloser:Lorg/eclipse/jface/text/contentassist/PopupCloser;
     482: aload_0
     483: getfield      #104                // Field fContentAssistant:Lorg/eclipse/jface/text/contentassist/ContentAssistant;
     486: aload_0
     487: getfield      #280                // Field fProposalTable:Lorg/eclipse/swt/widgets/Table;
     490: aload_0
     491: getfield      #108                // Field fAdditionalInfoController:Lorg/eclipse/jface/text/contentassist/AdditionalInfoController;
     494: invokevirtual #443                // Method org/eclipse/jface/text/contentassist/PopupCloser.install:(Lorg/eclipse/jface/text/contentassist/ContentAssistant;Lorg/eclipse/swt/widgets/Table;Lorg/eclipse/jface/text/contentassist/AdditionalInfoController;)V
     497: aload_0
     498: getfield      #142                // Field fProposalShell:Lorg/eclipse/swt/widgets/Shell;
     501: aload_0
     502: invokedynamic #446,  0            // InvokeDynamic #2:widgetDisposed:(Lorg/eclipse/jface/text/contentassist/CompletionProposalPopup;)Lorg/eclipse/swt/events/DisposeListener;
     507: invokevirtual #450                // Method org/eclipse/swt/widgets/Shell.addDisposeListener:(Lorg/eclipse/swt/events/DisposeListener;)V
     510: aload_0
     511: getfield      #280                // Field fProposalTable:Lorg/eclipse/swt/widgets/Table;
     514: iconst_0
     515: invokevirtual #454                // Method org/eclipse/swt/widgets/Table.setHeaderVisible:(Z)V
     518: aload_0
     519: aload_0
     520: getfield      #280                // Field fProposalTable:Lorg/eclipse/swt/widgets/Table;
     523: invokevirtual #457                // Method addCommandSupport:(Lorg/eclipse/swt/widgets/Control;)V
     526: return

  int getMinimalHeight();
    Code:
       0: iconst_0
       1: istore_1
       2: aload_0
       3: getfield      #280                // Field fProposalTable:Lorg/eclipse/swt/widgets/Table;
       6: invokestatic  #144                // Method org/eclipse/jface/util/Util.isValid:(Lorg/eclipse/swt/widgets/Widget;)Z
       9: ifeq          40
      12: aload_0
      13: getfield      #280                // Field fProposalTable:Lorg/eclipse/swt/widgets/Table;
      16: invokevirtual #348                // Method org/eclipse/swt/widgets/Table.getItemHeight:()I
      19: bipush        10
      21: imul
      22: istore_2
      23: aload_0
      24: getfield      #280                // Field fProposalTable:Lorg/eclipse/swt/widgets/Table;
      27: iconst_0
      28: iconst_0
      29: iconst_m1
      30: iload_2
      31: invokevirtual #382                // Method org/eclipse/swt/widgets/Table.computeTrim:(IIII)Lorg/eclipse/swt/graphics/Rectangle;
      34: astore_3
      35: aload_3
      36: getfield      #379                // Field org/eclipse/swt/graphics/Rectangle.height:I
      39: istore_1
      40: aload_0
      41: getfield      #485                // Field fMessageText:Lorg/eclipse/swt/widgets/Label;
      44: invokestatic  #144                // Method org/eclipse/jface/util/Util.isValid:(Lorg/eclipse/swt/widgets/Widget;)Z
      47: ifeq          65
      50: iload_1
      51: aload_0
      52: getfield      #485                // Field fMessageText:Lorg/eclipse/swt/widgets/Label;
      55: invokevirtual #487                // Method org/eclipse/swt/widgets/Label.getSize:()Lorg/eclipse/swt/graphics/Point;
      58: getfield      #492                // Field org/eclipse/swt/graphics/Point.y:I
      61: iconst_1
      62: iadd
      63: iadd
      64: istore_1
      65: iload_1
      66: ireturn

  private void addCommandSupport(org.eclipse.swt.widgets.Control);
    Code:
       0: aload_0
       1: getfield      #104                // Field fContentAssistant:Lorg/eclipse/jface/text/contentassist/ContentAssistant;
       4: invokevirtual #496                // Method org/eclipse/jface/text/contentassist/ContentAssistant.getRepeatedInvocationKeySequence:()Lorg/eclipse/jface/bindings/keys/KeySequence;
       7: astore_2
       8: aload_2
       9: ifnull        43
      12: aload_2
      13: invokevirtual #500                // Method org/eclipse/jface/bindings/keys/KeySequence.isEmpty:()Z
      16: ifne          43
      19: aload_0
      20: getfield      #104                // Field fContentAssistant:Lorg/eclipse/jface/text/contentassist/ContentAssistant;
      23: invokevirtual #204                // Method org/eclipse/jface/text/contentassist/ContentAssistant.isRepeatedInvocationMode:()Z
      26: ifeq          43
      29: aload_1
      30: new           #505                // class org/eclipse/jface/text/contentassist/CompletionProposalPopup$4
      33: dup
      34: aload_0
      35: aload_1
      36: aload_2
      37: invokespecial #507                // Method org/eclipse/jface/text/contentassist/CompletionProposalPopup$4."<init>":(Lorg/eclipse/jface/text/contentassist/CompletionProposalPopup;Lorg/eclipse/swt/widgets/Control;Lorg/eclipse/jface/bindings/keys/KeySequence;)V
      40: invokevirtual #510                // Method org/eclipse/swt/widgets/Control.addFocusListener:(Lorg/eclipse/swt/events/FocusListener;)V
      43: aload_0
      44: getfield      #108                // Field fAdditionalInfoController:Lorg/eclipse/jface/text/contentassist/AdditionalInfoController;
      47: ifnull        63
      50: aload_1
      51: new           #514                // class org/eclipse/jface/text/contentassist/CompletionProposalPopup$5
      54: dup
      55: aload_0
      56: aload_1
      57: invokespecial #516                // Method org/eclipse/jface/text/contentassist/CompletionProposalPopup$5."<init>":(Lorg/eclipse/jface/text/contentassist/CompletionProposalPopup;Lorg/eclipse/swt/widgets/Control;)V
      60: invokevirtual #510                // Method org/eclipse/swt/widgets/Control.addFocusListener:(Lorg/eclipse/swt/events/FocusListener;)V
      63: return

  private org.eclipse.swt.graphics.Color getBackgroundColor(org.eclipse.swt.widgets.Control);
    Code:
       0: aload_0
       1: getfield      #104                // Field fContentAssistant:Lorg/eclipse/jface/text/contentassist/ContentAssistant;
       4: invokevirtual #521                // Method org/eclipse/jface/text/contentassist/ContentAssistant.getProposalSelectorBackground:()Lorg/eclipse/swt/graphics/Color;
       7: astore_2
       8: aload_2
       9: ifnonnull     22
      12: invokestatic  #525                // Method org/eclipse/jface/resource/JFaceResources.getColorRegistry:()Lorg/eclipse/jface/resource/ColorRegistry;
      15: ldc_w         #529                // String CONTENT_ASSIST_BACKGROUND_COLOR
      18: invokevirtual #531                // Method org/eclipse/jface/resource/ColorRegistry.get:(Ljava/lang/String;)Lorg/eclipse/swt/graphics/Color;
      21: astore_2
      22: aload_2
      23: areturn

  private org.eclipse.swt.graphics.Color getForegroundColor(org.eclipse.swt.widgets.Control);
    Code:
       0: aload_0
       1: getfield      #104                // Field fContentAssistant:Lorg/eclipse/jface/text/contentassist/ContentAssistant;
       4: invokevirtual #538                // Method org/eclipse/jface/text/contentassist/ContentAssistant.getProposalSelectorForeground:()Lorg/eclipse/swt/graphics/Color;
       7: astore_2
       8: aload_2
       9: ifnonnull     22
      12: invokestatic  #525                // Method org/eclipse/jface/resource/JFaceResources.getColorRegistry:()Lorg/eclipse/jface/resource/ColorRegistry;
      15: ldc_w         #541                // String CONTENT_ASSIST_FOREGROUND_COLOR
      18: invokevirtual #531                // Method org/eclipse/jface/resource/ColorRegistry.get:(Ljava/lang/String;)Lorg/eclipse/swt/graphics/Color;
      21: astore_2
      22: aload_2
      23: areturn

  private void createMessageText();
    Code:
       0: aload_0
       1: getfield      #485                // Field fMessageText:Lorg/eclipse/swt/widgets/Label;
       4: ifnonnull     241
       7: aload_0
       8: new           #488                // class org/eclipse/swt/widgets/Label
      11: dup
      12: aload_0
      13: getfield      #142                // Field fProposalShell:Lorg/eclipse/swt/widgets/Shell;
      16: ldc_w         #543                // int 131072
      19: invokespecial #544                // Method org/eclipse/swt/widgets/Label."<init>":(Lorg/eclipse/swt/widgets/Composite;I)V
      22: putfield      #485                // Field fMessageText:Lorg/eclipse/swt/widgets/Label;
      25: new           #331                // class org/eclipse/swt/layout/GridData
      28: dup
      29: iconst_4
      30: sipush        1024
      33: iconst_1
      34: iconst_0
      35: invokespecial #545                // Method org/eclipse/swt/layout/GridData."<init>":(IIZZ)V
      38: astore_1
      39: aload_0
      40: getfield      #485                // Field fMessageText:Lorg/eclipse/swt/widgets/Label;
      43: aload_1
      44: invokevirtual #547                // Method org/eclipse/swt/widgets/Label.setLayoutData:(Ljava/lang/Object;)V
      47: aload_0
      48: getfield      #485                // Field fMessageText:Lorg/eclipse/swt/widgets/Label;
      51: aload_0
      52: getfield      #104                // Field fContentAssistant:Lorg/eclipse/jface/text/contentassist/ContentAssistant;
      55: invokevirtual #548                // Method org/eclipse/jface/text/contentassist/ContentAssistant.getStatusMessage:()Ljava/lang/String;
      58: invokedynamic #551,  0            // InvokeDynamic #3:makeConcatWithConstants:(Ljava/lang/String;)Ljava/lang/String;
      63: invokevirtual #555                // Method org/eclipse/swt/widgets/Label.setText:(Ljava/lang/String;)V
      66: aload_0
      67: getfield      #559                // Field fMessageTextFont:Lorg/eclipse/swt/graphics/Font;
      70: ifnonnull     156
      73: aload_0
      74: getfield      #485                // Field fMessageText:Lorg/eclipse/swt/widgets/Label;
      77: invokevirtual #561                // Method org/eclipse/swt/widgets/Label.getFont:()Lorg/eclipse/swt/graphics/Font;
      80: astore_2
      81: aload_0
      82: getfield      #142                // Field fProposalShell:Lorg/eclipse/swt/widgets/Shell;
      85: invokevirtual #354                // Method org/eclipse/swt/widgets/Shell.getDisplay:()Lorg/eclipse/swt/widgets/Display;
      88: astore_3
      89: aload_2
      90: invokevirtual #564                // Method org/eclipse/swt/graphics/Font.getFontData:()[Lorg/eclipse/swt/graphics/FontData;
      93: astore        4
      95: aload         4
      97: dup
      98: astore        8
     100: arraylength
     101: istore        7
     103: iconst_0
     104: istore        6
     106: goto          135
     109: aload         8
     111: iload         6
     113: aaload
     114: astore        5
     116: aload         5
     118: aload         5
     120: invokevirtual #570                // Method org/eclipse/swt/graphics/FontData.getHeight:()I
     123: bipush        9
     125: imul
     126: bipush        10
     128: idiv
     129: invokevirtual #575                // Method org/eclipse/swt/graphics/FontData.setHeight:(I)V
     132: iinc          6, 1
     135: iload         6
     137: iload         7
     139: if_icmplt     109
     142: aload_0
     143: new           #565                // class org/eclipse/swt/graphics/Font
     146: dup
     147: aload_3
     148: aload         4
     150: invokespecial #578                // Method org/eclipse/swt/graphics/Font."<init>":(Lorg/eclipse/swt/graphics/Device;[Lorg/eclipse/swt/graphics/FontData;)V
     153: putfield      #559                // Field fMessageTextFont:Lorg/eclipse/swt/graphics/Font;
     156: aload_0
     157: getfield      #485                // Field fMessageText:Lorg/eclipse/swt/widgets/Label;
     160: aload_0
     161: getfield      #559                // Field fMessageTextFont:Lorg/eclipse/swt/graphics/Font;
     164: invokevirtual #581                // Method org/eclipse/swt/widgets/Label.setFont:(Lorg/eclipse/swt/graphics/Font;)V
     167: aload_0
     168: getfield      #485                // Field fMessageText:Lorg/eclipse/swt/widgets/Label;
     171: aload_0
     172: aload_0
     173: getfield      #142                // Field fProposalShell:Lorg/eclipse/swt/widgets/Shell;
     176: invokevirtual #409                // Method getBackgroundColor:(Lorg/eclipse/swt/widgets/Control;)Lorg/eclipse/swt/graphics/Color;
     179: invokevirtual #582                // Method org/eclipse/swt/widgets/Label.setBackground:(Lorg/eclipse/swt/graphics/Color;)V
     182: aload_0
     183: getfield      #485                // Field fMessageText:Lorg/eclipse/swt/widgets/Label;
     186: aload_0
     187: aload_0
     188: getfield      #142                // Field fProposalShell:Lorg/eclipse/swt/widgets/Shell;
     191: invokevirtual #422                // Method getForegroundColor:(Lorg/eclipse/swt/widgets/Control;)Lorg/eclipse/swt/graphics/Color;
     194: invokevirtual #583                // Method org/eclipse/swt/widgets/Label.setForeground:(Lorg/eclipse/swt/graphics/Color;)V
     197: aload_0
     198: getfield      #104                // Field fContentAssistant:Lorg/eclipse/jface/text/contentassist/ContentAssistant;
     201: invokevirtual #204                // Method org/eclipse/jface/text/contentassist/ContentAssistant.isRepeatedInvocationMode:()Z
     204: ifeq          241
     207: aload_0
     208: getfield      #485                // Field fMessageText:Lorg/eclipse/swt/widgets/Label;
     211: aload_0
     212: getfield      #142                // Field fProposalShell:Lorg/eclipse/swt/widgets/Shell;
     215: invokevirtual #354                // Method org/eclipse/swt/widgets/Shell.getDisplay:()Lorg/eclipse/swt/widgets/Display;
     218: bipush        21
     220: invokevirtual #584                // Method org/eclipse/swt/widgets/Display.getSystemCursor:(I)Lorg/eclipse/swt/graphics/Cursor;
     223: invokevirtual #588                // Method org/eclipse/swt/widgets/Label.setCursor:(Lorg/eclipse/swt/graphics/Cursor;)V
     226: aload_0
     227: getfield      #485                // Field fMessageText:Lorg/eclipse/swt/widgets/Label;
     230: new           #592                // class org/eclipse/jface/text/contentassist/CompletionProposalPopup$6
     233: dup
     234: aload_0
     235: invokespecial #594                // Method org/eclipse/jface/text/contentassist/CompletionProposalPopup$6."<init>":(Lorg/eclipse/jface/text/contentassist/CompletionProposalPopup;)V
     238: invokevirtual #595                // Method org/eclipse/swt/widgets/Label.addMouseListener:(Lorg/eclipse/swt/events/MouseListener;)V
     241: return

  private void handleSetData(org.eclipse.swt.widgets.Event);
    Code:
       0: aload_1
       1: getfield      #610                // Field org/eclipse/swt/widgets/Event.item:Lorg/eclipse/swt/widgets/Widget;
       4: checkcast     #616                // class org/eclipse/swt/widgets/TableItem
       7: astore_2
       8: aload_0
       9: getfield      #280                // Field fProposalTable:Lorg/eclipse/swt/widgets/Table;
      12: aload_2
      13: invokevirtual #618                // Method org/eclipse/swt/widgets/Table.indexOf:(Lorg/eclipse/swt/widgets/TableItem;)I
      16: istore_3
      17: aload_0
      18: getfield      #622                // Field fFilteredProposals:Ljava/util/List;
      21: astore        4
      23: iload_3
      24: iflt          315
      27: iload_3
      28: aload         4
      30: invokeinterface #624,  1          // InterfaceMethod java/util/List.size:()I
      35: if_icmpge     315
      38: aload         4
      40: iload_3
      41: invokeinterface #626,  2          // InterfaceMethod java/util/List.get:(I)Ljava/lang/Object;
      46: checkcast     #629                // class org/eclipse/jface/text/contentassist/ICompletionProposal
      49: astore        5
      51: aconst_null
      52: astore        7
      54: aconst_null
      55: astore        8
      57: aload_0
      58: getfield      #102                // Field fIsColoredLabelsSupportEnabled:Z
      61: ifeq          163
      64: aload         5
      66: instanceof    #631                // class org/eclipse/jface/text/contentassist/ICompletionProposalExtension7
      69: ifeq          163
      72: aload_0
      73: getfield      #142                // Field fProposalShell:Lorg/eclipse/swt/widgets/Shell;
      76: invokestatic  #144                // Method org/eclipse/jface/util/Util.isValid:(Lorg/eclipse/swt/widgets/Widget;)Z
      79: ifeq          163
      82: aload_0
      83: getfield      #104                // Field fContentAssistant:Lorg/eclipse/jface/text/contentassist/ContentAssistant;
      86: invokevirtual #633                // Method org/eclipse/jface/text/contentassist/ContentAssistant.getBoldStylerProvider:()Lorg/eclipse/jface/text/contentassist/BoldStylerProvider;
      89: astore        9
      91: aload         9
      93: ifnonnull     121
      96: new           #637                // class org/eclipse/jface/text/contentassist/BoldStylerProvider
      99: dup
     100: aload_0
     101: getfield      #142                // Field fProposalShell:Lorg/eclipse/swt/widgets/Shell;
     104: invokevirtual #639                // Method org/eclipse/swt/widgets/Shell.getFont:()Lorg/eclipse/swt/graphics/Font;
     107: invokespecial #640                // Method org/eclipse/jface/text/contentassist/BoldStylerProvider."<init>":(Lorg/eclipse/swt/graphics/Font;)V
     110: astore        9
     112: aload_0
     113: getfield      #104                // Field fContentAssistant:Lorg/eclipse/jface/text/contentassist/ContentAssistant;
     116: aload         9
     118: invokevirtual #642                // Method org/eclipse/jface/text/contentassist/ContentAssistant.setBoldStylerProvider:(Lorg/eclipse/jface/text/contentassist/BoldStylerProvider;)V
     121: aload         5
     123: checkcast     #631                // class org/eclipse/jface/text/contentassist/ICompletionProposalExtension7
     126: aload_0
     127: getfield      #115                // Field fContentAssistSubjectControlAdapter:Lorg/eclipse/jface/text/contentassist/ContentAssistSubjectControlAdapter;
     130: invokevirtual #646                // Method org/eclipse/jface/text/contentassist/ContentAssistSubjectControlAdapter.getDocument:()Lorg/eclipse/jface/text/IDocument;
     133: aload_0
     134: getfield      #174                // Field fFilterOffset:I
     137: aload         9
     139: invokeinterface #650,  4          // InterfaceMethod org/eclipse/jface/text/contentassist/ICompletionProposalExtension7.getStyledDisplayString:(Lorg/eclipse/jface/text/IDocument;ILorg/eclipse/jface/text/contentassist/BoldStylerProvider;)Lorg/eclipse/jface/viewers/StyledString;
     144: astore        10
     146: aload         10
     148: invokevirtual #654                // Method org/eclipse/jface/viewers/StyledString.getString:()Ljava/lang/String;
     151: astore        6
     153: aload         10
     155: invokevirtual #659                // Method org/eclipse/jface/viewers/StyledString.getStyleRanges:()[Lorg/eclipse/swt/custom/StyleRange;
     158: astore        7
     160: goto          270
     163: aload_0
     164: getfield      #102                // Field fIsColoredLabelsSupportEnabled:Z
     167: ifeq          207
     170: aload         5
     172: instanceof    #663                // class org/eclipse/jface/text/contentassist/ICompletionProposalExtension6
     175: ifeq          207
     178: aload         5
     180: checkcast     #663                // class org/eclipse/jface/text/contentassist/ICompletionProposalExtension6
     183: invokeinterface #665,  1          // InterfaceMethod org/eclipse/jface/text/contentassist/ICompletionProposalExtension6.getStyledDisplayString:()Lorg/eclipse/jface/viewers/StyledString;
     188: astore        9
     190: aload         9
     192: invokevirtual #654                // Method org/eclipse/jface/viewers/StyledString.getString:()Ljava/lang/String;
     195: astore        6
     197: aload         9
     199: invokevirtual #659                // Method org/eclipse/jface/viewers/StyledString.getStyleRanges:()[Lorg/eclipse/swt/custom/StyleRange;
     202: astore        7
     204: goto          270
     207: aload         5
     209: invokeinterface #668,  1          // InterfaceMethod org/eclipse/jface/text/contentassist/ICompletionProposal.getDisplayString:()Ljava/lang/String;
     214: astore        6
     216: goto          270
     219: astore        9
     221: ldc_w         #671                // String CompletionProposalPopup.error_retrieving_proposal
     224: invokestatic  #673                // Method org/eclipse/jface/text/contentassist/JFaceTextMessages.getString:(Ljava/lang/String;)Ljava/lang/String;
     227: astore        6
     229: ldc_w         #677                // String org.eclipse.jface.text
     232: astore        10
     234: aload         10
     236: invokestatic  #679                // Method org/eclipse/core/runtime/Platform.getBundle:(Ljava/lang/String;)Lorg/osgi/framework/Bundle;
     239: invokestatic  #685                // InterfaceMethod org/eclipse/core/runtime/ILog.of:(Lorg/osgi/framework/Bundle;)Lorg/eclipse/core/runtime/ILog;
     242: astore        11
     244: aload         11
     246: new           #691                // class org/eclipse/core/runtime/Status
     249: dup
     250: iconst_4
     251: aload         10
     253: iconst_0
     254: ldc_w         #693                // String CompletionProposalPopup.unexpected_error
     257: invokestatic  #673                // Method org/eclipse/jface/text/contentassist/JFaceTextMessages.getString:(Ljava/lang/String;)Ljava/lang/String;
     260: aload         9
     262: invokespecial #695                // Method org/eclipse/core/runtime/Status."<init>":(ILjava/lang/String;ILjava/lang/String;Ljava/lang/Throwable;)V
     265: invokeinterface #698,  2          // InterfaceMethod org/eclipse/core/runtime/ILog.log:(Lorg/eclipse/core/runtime/IStatus;)V
     270: aload         5
     272: invokeinterface #702,  1          // InterfaceMethod org/eclipse/jface/text/contentassist/ICompletionProposal.getImage:()Lorg/eclipse/swt/graphics/Image;
     277: astore        8
     279: goto          283
     282: pop
     283: aload_2
     284: aload         6
     286: invokevirtual #706                // Method org/eclipse/swt/widgets/TableItem.setText:(Ljava/lang/String;)V
     289: aload_0
     290: getfield      #102                // Field fIsColoredLabelsSupportEnabled:Z
     293: ifeq          303
     296: aload_2
     297: iconst_0
     298: aload         7
     300: invokestatic  #707                // Method org/eclipse/jface/internal/text/TableOwnerDrawSupport.storeStyleRanges:(Lorg/eclipse/swt/widgets/TableItem;I[Lorg/eclipse/swt/custom/StyleRange;)V
     303: aload_2
     304: aload         8
     306: invokevirtual #711                // Method org/eclipse/swt/widgets/TableItem.setImage:(Lorg/eclipse/swt/graphics/Image;)V
     309: aload_2
     310: aload         5
     312: invokevirtual #715                // Method org/eclipse/swt/widgets/TableItem.setData:(Ljava/lang/Object;)V
     315: return
    Exception table:
       from    to  target type
          57   216   219   Class java/lang/RuntimeException
         270   279   282   Class java/lang/RuntimeException

  private org.eclipse.jface.text.contentassist.ICompletionProposal getSelectedProposal();
    Code:
       0: aload_0
       1: getfield      #93                 // Field fIsFilterPending:Ljava/util/concurrent/atomic/AtomicBoolean;
       4: invokevirtual #745                // Method java/util/concurrent/atomic/AtomicBoolean.get:()Z
       7: ifeq          19
      10: aload_0
      11: getfield      #86                 // Field fFilterRunnable:Ljava/lang/Runnable;
      14: invokeinterface #747,  1          // InterfaceMethod java/lang/Runnable.run:()V
      19: aload_0
      20: getfield      #280                // Field fProposalTable:Lorg/eclipse/swt/widgets/Table;
      23: invokestatic  #144                // Method org/eclipse/jface/util/Util.isValid:(Lorg/eclipse/swt/widgets/Widget;)Z
      26: ifne          31
      29: aconst_null
      30: areturn
      31: aload_0
      32: getfield      #280                // Field fProposalTable:Lorg/eclipse/swt/widgets/Table;
      35: invokevirtual #751                // Method org/eclipse/swt/widgets/Table.getSelectionIndex:()I
      38: istore_1
      39: aload_0
      40: getfield      #622                // Field fFilteredProposals:Ljava/util/List;
      43: astore_2
      44: aload_2
      45: ifnull        62
      48: iload_1
      49: iflt          62
      52: iload_1
      53: aload_2
      54: invokeinterface #624,  1          // InterfaceMethod java/util/List.size:()I
      59: if_icmplt     64
      62: aconst_null
      63: areturn
      64: aload_2
      65: iload_1
      66: invokeinterface #626,  2          // InterfaceMethod java/util/List.get:(I)Ljava/lang/Object;
      71: checkcast     #629                // class org/eclipse/jface/text/contentassist/ICompletionProposal
      74: areturn

  private void insertSelectedProposalWithMask(int);
    Code:
       0: aload_0
       1: invokevirtual #756                // Method getSelectedProposal:()Lorg/eclipse/jface/text/contentassist/ICompletionProposal;
       4: astore_2
       5: aload_0
       6: invokevirtual #201                // Method hide:()V
       9: aload_2
      10: ifnull        30
      13: aload_0
      14: aload_2
      15: iconst_0
      16: iload_1
      17: aload_0
      18: getfield      #115                // Field fContentAssistSubjectControlAdapter:Lorg/eclipse/jface/text/contentassist/ContentAssistSubjectControlAdapter;
      21: invokevirtual #758                // Method org/eclipse/jface/text/contentassist/ContentAssistSubjectControlAdapter.getSelectedRange:()Lorg/eclipse/swt/graphics/Point;
      24: getfield      #761                // Field org/eclipse/swt/graphics/Point.x:I
      27: invokevirtual #764                // Method insertProposal:(Lorg/eclipse/jface/text/contentassist/ICompletionProposal;CII)V
      30: return

  void insertProposal(org.eclipse.jface.text.contentassist.ICompletionProposal, char, int, int);
    Code:
       0: aload_0
       1: iconst_1
       2: putfield      #74                 // Field fInserting:Z
       5: aconst_null
       6: astore        5
       8: new           #770                // class org/eclipse/jface/text/contentassist/CompletionProposalPopup$7
      11: dup
      12: aload_0
      13: iload         4
      15: invokespecial #772                // Method org/eclipse/jface/text/contentassist/CompletionProposalPopup$7."<init>":(Lorg/eclipse/jface/text/contentassist/CompletionProposalPopup;I)V
      18: astore        6
      20: aload_0
      21: getfield      #115                // Field fContentAssistSubjectControlAdapter:Lorg/eclipse/jface/text/contentassist/ContentAssistSubjectControlAdapter;
      24: invokevirtual #646                // Method org/eclipse/jface/text/contentassist/ContentAssistSubjectControlAdapter.getDocument:()Lorg/eclipse/jface/text/IDocument;
      27: astore        7
      29: aload_0
      30: getfield      #106                // Field fViewer:Lorg/eclipse/jface/text/ITextViewer;
      33: instanceof    #775                // class org/eclipse/jface/text/ITextViewerExtension
      36: ifeq          57
      39: aload_0
      40: getfield      #106                // Field fViewer:Lorg/eclipse/jface/text/ITextViewer;
      43: checkcast     #775                // class org/eclipse/jface/text/ITextViewerExtension
      46: astore        8
      48: aload         8
      50: invokeinterface #777,  1          // InterfaceMethod org/eclipse/jface/text/ITextViewerExtension.getRewriteTarget:()Lorg/eclipse/jface/text/IRewriteTarget;
      55: astore        5
      57: aload         5
      59: ifnull        69
      62: aload         5
      64: invokeinterface #781,  1          // InterfaceMethod org/eclipse/jface/text/IRewriteTarget.beginCompoundChange:()V
      69: aload_0
      70: getfield      #106                // Field fViewer:Lorg/eclipse/jface/text/ITextViewer;
      73: instanceof    #786                // class org/eclipse/jface/text/IEditingSupportRegistry
      76: ifeq          97
      79: aload_0
      80: getfield      #106                // Field fViewer:Lorg/eclipse/jface/text/ITextViewer;
      83: checkcast     #786                // class org/eclipse/jface/text/IEditingSupportRegistry
      86: astore        8
      88: aload         8
      90: aload         6
      92: invokeinterface #788,  2          // InterfaceMethod org/eclipse/jface/text/IEditingSupportRegistry.register:(Lorg/eclipse/jface/text/IEditingSupport;)V
      97: aload_1
      98: instanceof    #792                // class org/eclipse/jface/text/contentassist/ICompletionProposalExtension2
     101: ifeq          135
     104: aload_0
     105: getfield      #106                // Field fViewer:Lorg/eclipse/jface/text/ITextViewer;
     108: ifnull        135
     111: aload_1
     112: checkcast     #792                // class org/eclipse/jface/text/contentassist/ICompletionProposalExtension2
     115: astore        8
     117: aload         8
     119: aload_0
     120: getfield      #106                // Field fViewer:Lorg/eclipse/jface/text/ITextViewer;
     123: iload_2
     124: iload_3
     125: iload         4
     127: invokeinterface #794,  5          // InterfaceMethod org/eclipse/jface/text/contentassist/ICompletionProposalExtension2.apply:(Lorg/eclipse/jface/text/ITextViewer;CII)V
     132: goto          171
     135: aload_1
     136: instanceof    #798                // class org/eclipse/jface/text/contentassist/ICompletionProposalExtension
     139: ifeq          163
     142: aload_1
     143: checkcast     #798                // class org/eclipse/jface/text/contentassist/ICompletionProposalExtension
     146: astore        8
     148: aload         8
     150: aload         7
     152: iload_2
     153: iload         4
     155: invokeinterface #800,  4          // InterfaceMethod org/eclipse/jface/text/contentassist/ICompletionProposalExtension.apply:(Lorg/eclipse/jface/text/IDocument;CI)V
     160: goto          171
     163: aload_1
     164: aload         7
     166: invokeinterface #803,  2          // InterfaceMethod org/eclipse/jface/text/contentassist/ICompletionProposal.apply:(Lorg/eclipse/jface/text/IDocument;)V
     171: aload_0
     172: aload_1
     173: invokevirtual #806                // Method fireAppliedEvent:(Lorg/eclipse/jface/text/contentassist/ICompletionProposal;)V
     176: aload_1
     177: aload         7
     179: invokeinterface #810,  2          // InterfaceMethod org/eclipse/jface/text/contentassist/ICompletionProposal.getSelection:(Lorg/eclipse/jface/text/IDocument;)Lorg/eclipse/swt/graphics/Point;
     184: astore        8
     186: aload         8
     188: ifnull        225
     191: aload_0
     192: getfield      #115                // Field fContentAssistSubjectControlAdapter:Lorg/eclipse/jface/text/contentassist/ContentAssistSubjectControlAdapter;
     195: aload         8
     197: getfield      #761                // Field org/eclipse/swt/graphics/Point.x:I
     200: aload         8
     202: getfield      #492                // Field org/eclipse/swt/graphics/Point.y:I
     205: invokevirtual #814                // Method org/eclipse/jface/text/contentassist/ContentAssistSubjectControlAdapter.setSelectedRange:(II)V
     208: aload_0
     209: getfield      #115                // Field fContentAssistSubjectControlAdapter:Lorg/eclipse/jface/text/contentassist/ContentAssistSubjectControlAdapter;
     212: aload         8
     214: getfield      #761                // Field org/eclipse/swt/graphics/Point.x:I
     217: aload         8
     219: getfield      #492                // Field org/eclipse/swt/graphics/Point.y:I
     222: invokevirtual #817                // Method org/eclipse/jface/text/contentassist/ContentAssistSubjectControlAdapter.revealRange:(II)V
     225: aload_1
     226: invokeinterface #820,  1          // InterfaceMethod org/eclipse/jface/text/contentassist/ICompletionProposal.getContextInformation:()Lorg/eclipse/jface/text/contentassist/IContextInformation;
     231: astore        9
     233: aload         9
     235: ifnull        304
     238: aload_1
     239: instanceof    #798                // class org/eclipse/jface/text/contentassist/ICompletionProposalExtension
     242: ifeq          263
     245: aload_1
     246: checkcast     #798                // class org/eclipse/jface/text/contentassist/ICompletionProposalExtension
     249: astore        11
     251: aload         11
     253: invokeinterface #824,  1          // InterfaceMethod org/eclipse/jface/text/contentassist/ICompletionProposalExtension.getContextInformationPosition:()I
     258: istore        10
     260: goto          290
     263: aload         8
     265: ifnonnull     277
     268: aload_0
     269: getfield      #115                // Field fContentAssistSubjectControlAdapter:Lorg/eclipse/jface/text/contentassist/ContentAssistSubjectControlAdapter;
     272: invokevirtual #758                // Method org/eclipse/jface/text/contentassist/ContentAssistSubjectControlAdapter.getSelectedRange:()Lorg/eclipse/swt/graphics/Point;
     275: astore        8
     277: aload         8
     279: getfield      #761                // Field org/eclipse/swt/graphics/Point.x:I
     282: aload         8
     284: getfield      #492                // Field org/eclipse/swt/graphics/Point.y:I
     287: iadd
     288: istore        10
     290: aload_0
     291: getfield      #104                // Field fContentAssistant:Lorg/eclipse/jface/text/contentassist/ContentAssistant;
     294: aload         9
     296: iload         10
     298: invokevirtual #827                // Method org/eclipse/jface/text/contentassist/ContentAssistant.showContextInformation:(Lorg/eclipse/jface/text/contentassist/IContextInformation;I)V
     301: goto          366
     304: aload_0
     305: getfield      #104                // Field fContentAssistant:Lorg/eclipse/jface/text/contentassist/ContentAssistant;
     308: aconst_null
     309: iconst_m1
     310: invokevirtual #827                // Method org/eclipse/jface/text/contentassist/ContentAssistant.showContextInformation:(Lorg/eclipse/jface/text/contentassist/IContextInformation;I)V
     313: goto          366
     316: astore        12
     318: aload         5
     320: ifnull        330
     323: aload         5
     325: invokeinterface #831,  1          // InterfaceMethod org/eclipse/jface/text/IRewriteTarget.endCompoundChange:()V
     330: aload_0
     331: getfield      #106                // Field fViewer:Lorg/eclipse/jface/text/ITextViewer;
     334: instanceof    #786                // class org/eclipse/jface/text/IEditingSupportRegistry
     337: ifeq          358
     340: aload_0
     341: getfield      #106                // Field fViewer:Lorg/eclipse/jface/text/ITextViewer;
     344: checkcast     #786                // class org/eclipse/jface/text/IEditingSupportRegistry
     347: astore        13
     349: aload         13
     351: aload         6
     353: invokeinterface #834,  2          // InterfaceMethod org/eclipse/jface/text/IEditingSupportRegistry.unregister:(Lorg/eclipse/jface/text/IEditingSupport;)V
     358: aload_0
     359: iconst_0
     360: putfield      #74                 // Field fInserting:Z
     363: aload         12
     365: athrow
     366: aload         5
     368: ifnull        378
     371: aload         5
     373: invokeinterface #831,  1          // InterfaceMethod org/eclipse/jface/text/IRewriteTarget.endCompoundChange:()V
     378: aload_0
     379: getfield      #106                // Field fViewer:Lorg/eclipse/jface/text/ITextViewer;
     382: instanceof    #786                // class org/eclipse/jface/text/IEditingSupportRegistry
     385: ifeq          406
     388: aload_0
     389: getfield      #106                // Field fViewer:Lorg/eclipse/jface/text/ITextViewer;
     392: checkcast     #786                // class org/eclipse/jface/text/IEditingSupportRegistry
     395: astore        13
     397: aload         13
     399: aload         6
     401: invokeinterface #834,  2          // InterfaceMethod org/eclipse/jface/text/IEditingSupportRegistry.unregister:(Lorg/eclipse/jface/text/IEditingSupport;)V
     406: aload_0
     407: iconst_0
     408: putfield      #74                 // Field fInserting:Z
     411: return
    Exception table:
       from    to  target type
          20   316   316   any

  public boolean hasFocus();
    Code:
       0: aload_0
       1: getfield      #142                // Field fProposalShell:Lorg/eclipse/swt/widgets/Shell;
       4: invokestatic  #144                // Method org/eclipse/jface/util/Util.isValid:(Lorg/eclipse/swt/widgets/Widget;)Z
       7: ifeq          94
      10: aload_0
      11: getfield      #142                // Field fProposalShell:Lorg/eclipse/swt/widgets/Shell;
      14: invokevirtual #354                // Method org/eclipse/swt/widgets/Shell.getDisplay:()Lorg/eclipse/swt/widgets/Display;
      17: invokevirtual #863                // Method org/eclipse/swt/widgets/Display.getActiveShell:()Lorg/eclipse/swt/widgets/Shell;
      20: aload_0
      21: getfield      #142                // Field fProposalShell:Lorg/eclipse/swt/widgets/Shell;
      24: if_acmpne     29
      27: iconst_1
      28: ireturn
      29: aload_0
      30: getfield      #108                // Field fAdditionalInfoController:Lorg/eclipse/jface/text/contentassist/AdditionalInfoController;
      33: ifnull        94
      36: aload_0
      37: getfield      #108                // Field fAdditionalInfoController:Lorg/eclipse/jface/text/contentassist/AdditionalInfoController;
      40: invokevirtual #866                // Method org/eclipse/jface/text/contentassist/AdditionalInfoController.getCurrentInformationControl2:()Lorg/eclipse/jface/text/IInformationControl;
      43: astore_1
      44: aload_1
      45: ifnull        59
      48: aload_1
      49: invokeinterface #870,  1          // InterfaceMethod org/eclipse/jface/text/IInformationControl.isFocusControl:()Z
      54: ifeq          59
      57: iconst_1
      58: ireturn
      59: aload_0
      60: getfield      #108                // Field fAdditionalInfoController:Lorg/eclipse/jface/text/contentassist/AdditionalInfoController;
      63: invokevirtual #875                // Method org/eclipse/jface/text/contentassist/AdditionalInfoController.getInternalAccessor:()Lorg/eclipse/jface/internal/text/InternalAccessor;
      66: invokevirtual #879                // Method org/eclipse/jface/internal/text/InternalAccessor.getInformationControlReplacer:()Lorg/eclipse/jface/internal/text/InformationControlReplacer;
      69: astore_2
      70: aload_2
      71: ifnull        94
      74: aload_2
      75: invokevirtual #885                // Method org/eclipse/jface/internal/text/InformationControlReplacer.getCurrentInformationControl2:()Lorg/eclipse/jface/text/IInformationControl;
      78: astore_1
      79: aload_1
      80: ifnull        94
      83: aload_1
      84: invokeinterface #870,  1          // InterfaceMethod org/eclipse/jface/text/IInformationControl.isFocusControl:()Z
      89: ifeq          94
      92: iconst_1
      93: ireturn
      94: iconst_0
      95: ireturn

  public void hide();
    Code:
       0: aload_0
       1: invokevirtual #892                // Method unregister:()V
       4: aload_0
       5: getfield      #106                // Field fViewer:Lorg/eclipse/jface/text/ITextViewer;
       8: instanceof    #786                // class org/eclipse/jface/text/IEditingSupportRegistry
      11: ifeq          32
      14: aload_0
      15: getfield      #106                // Field fViewer:Lorg/eclipse/jface/text/ITextViewer;
      18: checkcast     #786                // class org/eclipse/jface/text/IEditingSupportRegistry
      21: astore_1
      22: aload_1
      23: aload_0
      24: getfield      #894                // Field fFocusHelper:Lorg/eclipse/jface/text/IEditingSupport;
      27: invokeinterface #834,  2          // InterfaceMethod org/eclipse/jface/text/IEditingSupportRegistry.unregister:(Lorg/eclipse/jface/text/IEditingSupport;)V
      32: aload_0
      33: getfield      #142                // Field fProposalShell:Lorg/eclipse/swt/widgets/Shell;
      36: invokestatic  #144                // Method org/eclipse/jface/util/Util.isValid:(Lorg/eclipse/swt/widgets/Widget;)Z
      39: ifeq          78
      42: aload_0
      43: getfield      #104                // Field fContentAssistant:Lorg/eclipse/jface/text/contentassist/ContentAssistant;
      46: aload_0
      47: iconst_1
      48: invokevirtual #896                // Method org/eclipse/jface/text/contentassist/ContentAssistant.removeContentAssistListener:(Lorg/eclipse/jface/text/contentassist/IContentAssistListener;I)V
      51: aload_0
      52: getfield      #72                 // Field fPopupCloser:Lorg/eclipse/jface/text/contentassist/PopupCloser;
      55: invokevirtual #900                // Method org/eclipse/jface/text/contentassist/PopupCloser.uninstall:()V
      58: aload_0
      59: getfield      #142                // Field fProposalShell:Lorg/eclipse/swt/widgets/Shell;
      62: iconst_0
      63: invokevirtual #903                // Method org/eclipse/swt/widgets/Shell.setVisible:(Z)V
      66: aload_0
      67: getfield      #142                // Field fProposalShell:Lorg/eclipse/swt/widgets/Shell;
      70: invokevirtual #906                // Method org/eclipse/swt/widgets/Shell.dispose:()V
      73: aload_0
      74: aconst_null
      75: putfield      #142                // Field fProposalShell:Lorg/eclipse/swt/widgets/Shell;
      78: aload_0
      79: getfield      #559                // Field fMessageTextFont:Lorg/eclipse/swt/graphics/Font;
      82: ifnull        97
      85: aload_0
      86: getfield      #559                // Field fMessageTextFont:Lorg/eclipse/swt/graphics/Font;
      89: invokevirtual #909                // Method org/eclipse/swt/graphics/Font.dispose:()V
      92: aload_0
      93: aconst_null
      94: putfield      #559                // Field fMessageTextFont:Lorg/eclipse/swt/graphics/Font;
      97: aload_0
      98: getfield      #485                // Field fMessageText:Lorg/eclipse/swt/widgets/Label;
     101: ifnull        109
     104: aload_0
     105: aconst_null
     106: putfield      #485                // Field fMessageText:Lorg/eclipse/swt/widgets/Label;
     109: aload_0
     110: aconst_null
     111: putfield      #100                // Field fEmptyMessage:Ljava/lang/String;
     114: aload_0
     115: iconst_m1
     116: putfield      #176                // Field fLastCompletionOffset:I
     119: aload_0
     120: getfield      #104                // Field fContentAssistant:Lorg/eclipse/jface/text/contentassist/ContentAssistant;
     123: invokevirtual #910                // Method org/eclipse/jface/text/contentassist/ContentAssistant.fireSessionEndEvent:()V
     126: return

  private void unregister();
    Code:
       0: aload_0
       1: getfield      #913                // Field fDocumentListener:Lorg/eclipse/jface/text/IDocumentListener;
       4: ifnull        34
       7: aload_0
       8: getfield      #115                // Field fContentAssistSubjectControlAdapter:Lorg/eclipse/jface/text/contentassist/ContentAssistSubjectControlAdapter;
      11: invokevirtual #646                // Method org/eclipse/jface/text/contentassist/ContentAssistSubjectControlAdapter.getDocument:()Lorg/eclipse/jface/text/IDocument;
      14: astore_1
      15: aload_1
      16: ifnull        29
      19: aload_1
      20: aload_0
      21: getfield      #913                // Field fDocumentListener:Lorg/eclipse/jface/text/IDocumentListener;
      24: invokeinterface #915,  2          // InterfaceMethod org/eclipse/jface/text/IDocument.removeDocumentListener:(Lorg/eclipse/jface/text/IDocumentListener;)V
      29: aload_0
      30: aconst_null
      31: putfield      #913                // Field fDocumentListener:Lorg/eclipse/jface/text/IDocumentListener;
      34: aload_0
      35: getfield      #79                 // Field fDocumentEvents:Ljava/util/List;
      38: invokeinterface #919,  1          // InterfaceMethod java/util/List.clear:()V
      43: aload_0
      44: getfield      #133                // Field fKeyListener:Lorg/eclipse/jface/text/contentassist/CompletionProposalPopup$ProposalSelectionListener;
      47: ifnull        89
      50: aload_0
      51: getfield      #115                // Field fContentAssistSubjectControlAdapter:Lorg/eclipse/jface/text/contentassist/ContentAssistSubjectControlAdapter;
      54: invokevirtual #138                // Method org/eclipse/jface/text/contentassist/ContentAssistSubjectControlAdapter.getControl:()Lorg/eclipse/swt/widgets/Control;
      57: ifnull        89
      60: aload_0
      61: getfield      #115                // Field fContentAssistSubjectControlAdapter:Lorg/eclipse/jface/text/contentassist/ContentAssistSubjectControlAdapter;
      64: invokevirtual #138                // Method org/eclipse/jface/text/contentassist/ContentAssistSubjectControlAdapter.getControl:()Lorg/eclipse/swt/widgets/Control;
      67: invokevirtual #150                // Method org/eclipse/swt/widgets/Control.isDisposed:()Z
      70: ifne          89
      73: aload_0
      74: getfield      #115                // Field fContentAssistSubjectControlAdapter:Lorg/eclipse/jface/text/contentassist/ContentAssistSubjectControlAdapter;
      77: aload_0
      78: getfield      #133                // Field fKeyListener:Lorg/eclipse/jface/text/contentassist/CompletionProposalPopup$ProposalSelectionListener;
      81: invokevirtual #922                // Method org/eclipse/jface/text/contentassist/ContentAssistSubjectControlAdapter.removeKeyListener:(Lorg/eclipse/swt/events/KeyListener;)V
      84: aload_0
      85: aconst_null
      86: putfield      #133                // Field fKeyListener:Lorg/eclipse/jface/text/contentassist/CompletionProposalPopup$ProposalSelectionListener;
      89: aload_0
      90: getfield      #925                // Field fLastProposal:Lorg/eclipse/jface/text/contentassist/ICompletionProposal;
      93: ifnull        136
      96: aload_0
      97: getfield      #925                // Field fLastProposal:Lorg/eclipse/jface/text/contentassist/ICompletionProposal;
     100: instanceof    #792                // class org/eclipse/jface/text/contentassist/ICompletionProposalExtension2
     103: ifeq          131
     106: aload_0
     107: getfield      #106                // Field fViewer:Lorg/eclipse/jface/text/ITextViewer;
     110: ifnull        131
     113: aload_0
     114: getfield      #925                // Field fLastProposal:Lorg/eclipse/jface/text/contentassist/ICompletionProposal;
     117: checkcast     #792                // class org/eclipse/jface/text/contentassist/ICompletionProposalExtension2
     120: astore_1
     121: aload_1
     122: aload_0
     123: getfield      #106                // Field fViewer:Lorg/eclipse/jface/text/ITextViewer;
     126: invokeinterface #927,  2          // InterfaceMethod org/eclipse/jface/text/contentassist/ICompletionProposalExtension2.unselected:(Lorg/eclipse/jface/text/ITextViewer;)V
     131: aload_0
     132: aconst_null
     133: putfield      #925                // Field fLastProposal:Lorg/eclipse/jface/text/contentassist/ICompletionProposal;
     136: aload_0
     137: aconst_null
     138: putfield      #622                // Field fFilteredProposals:Ljava/util/List;
     141: aload_0
     142: aconst_null
     143: putfield      #211                // Field fComputedProposals:Ljava/util/List;
     146: aload_0
     147: getfield      #104                // Field fContentAssistant:Lorg/eclipse/jface/text/contentassist/ContentAssistant;
     150: invokevirtual #930                // Method org/eclipse/jface/text/contentassist/ContentAssistant.possibleCompletionsClosed:()V
     153: return

  public boolean isActive();
    Code:
       0: aload_0
       1: getfield      #142                // Field fProposalShell:Lorg/eclipse/swt/widgets/Shell;
       4: ifnull        19
       7: aload_0
       8: getfield      #142                // Field fProposalShell:Lorg/eclipse/swt/widgets/Shell;
      11: invokevirtual #934                // Method org/eclipse/swt/widgets/Shell.isDisposed:()Z
      14: ifne          19
      17: iconst_1
      18: ireturn
      19: iconst_0
      20: ireturn

  void setProposals(java.util.List<org.eclipse.jface.text.contentassist.ICompletionProposal>, boolean);
    Code:
       0: aload_0
       1: getfield      #622                // Field fFilteredProposals:Ljava/util/List;
       4: astore_3
       5: aload_0
       6: invokevirtual #756                // Method getSelectedProposal:()Lorg/eclipse/jface/text/contentassist/ICompletionProposal;
       9: astore        4
      11: aload_3
      12: aload_0
      13: getfield      #622                // Field fFilteredProposals:Ljava/util/List;
      16: if_acmpeq     20
      19: return
      20: aload_0
      21: getfield      #280                // Field fProposalTable:Lorg/eclipse/swt/widgets/Table;
      24: invokestatic  #144                // Method org/eclipse/jface/util/Util.isValid:(Lorg/eclipse/swt/widgets/Widget;)Z
      27: ifeq          240
      30: aload         4
      32: instanceof    #792                // class org/eclipse/jface/text/contentassist/ICompletionProposalExtension2
      35: ifeq          59
      38: aload_0
      39: getfield      #106                // Field fViewer:Lorg/eclipse/jface/text/ITextViewer;
      42: ifnull        59
      45: aload         4
      47: checkcast     #792                // class org/eclipse/jface/text/contentassist/ICompletionProposalExtension2
      50: aload_0
      51: getfield      #106                // Field fViewer:Lorg/eclipse/jface/text/ITextViewer;
      54: invokeinterface #927,  2          // InterfaceMethod org/eclipse/jface/text/contentassist/ICompletionProposalExtension2.unselected:(Lorg/eclipse/jface/text/ITextViewer;)V
      59: aload_1
      60: ifnull        72
      63: aload_1
      64: invokeinterface #936,  1          // InterfaceMethod java/util/List.isEmpty:()Z
      69: ifeq          118
      72: aload_0
      73: getfield      #98                 // Field fEmptyProposal:Lorg/eclipse/jface/text/contentassist/CompletionProposalPopup$EmptyProposal;
      76: aload_0
      77: getfield      #174                // Field fFilterOffset:I
      80: putfield      #937                // Field org/eclipse/jface/text/contentassist/CompletionProposalPopup$EmptyProposal.fOffset:I
      83: aload_0
      84: getfield      #98                 // Field fEmptyProposal:Lorg/eclipse/jface/text/contentassist/CompletionProposalPopup$EmptyProposal;
      87: aload_0
      88: getfield      #100                // Field fEmptyMessage:Ljava/lang/String;
      91: ifnull        101
      94: aload_0
      95: getfield      #100                // Field fEmptyMessage:Ljava/lang/String;
      98: goto          107
     101: ldc_w         #940                // String CompletionProposalPopup.no_proposals
     104: invokestatic  #673                // Method org/eclipse/jface/text/contentassist/JFaceTextMessages.getString:(Ljava/lang/String;)Ljava/lang/String;
     107: putfield      #942                // Field org/eclipse/jface/text/contentassist/CompletionProposalPopup$EmptyProposal.fDisplayString:Ljava/lang/String;
     110: aload_0
     111: getfield      #98                 // Field fEmptyProposal:Lorg/eclipse/jface/text/contentassist/CompletionProposalPopup$EmptyProposal;
     114: invokestatic  #945                // Method java/util/Collections.singletonList:(Ljava/lang/Object;)Ljava/util/List;
     117: astore_1
     118: aload_0
     119: getfield      #237                // Field fSorter:Lorg/eclipse/jface/text/contentassist/ICompletionProposalSorter;
     122: ifnull        137
     125: aload_0
     126: getfield      #243                // Field fIsInitialSort:Z
     129: ifne          137
     132: aload_0
     133: aload_1
     134: invokevirtual #239                // Method sortProposals:(Ljava/util/List;)V
     137: aload_0
     138: iconst_0
     139: putfield      #243                // Field fIsInitialSort:Z
     142: aload_0
     143: aload_1
     144: putfield      #622                // Field fFilteredProposals:Ljava/util/List;
     147: aload_1
     148: invokeinterface #624,  1          // InterfaceMethod java/util/List.size:()I
     153: istore        5
     155: aload_0
     156: getfield      #280                // Field fProposalTable:Lorg/eclipse/swt/widgets/Table;
     159: invokevirtual #949                // Method org/eclipse/swt/widgets/Table.clearAll:()V
     162: aload_0
     163: getfield      #280                // Field fProposalTable:Lorg/eclipse/swt/widgets/Table;
     166: iload         5
     168: invokevirtual #952                // Method org/eclipse/swt/widgets/Table.setItemCount:(I)V
     171: aload_0
     172: getfield      #142                // Field fProposalShell:Lorg/eclipse/swt/widgets/Shell;
     175: invokevirtual #955                // Method org/eclipse/swt/widgets/Shell.getLocation:()Lorg/eclipse/swt/graphics/Point;
     178: astore        6
     180: aload_0
     181: invokevirtual #355                // Method getLocation:()Lorg/eclipse/swt/graphics/Point;
     184: astore        7
     186: aload         7
     188: getfield      #761                // Field org/eclipse/swt/graphics/Point.x:I
     191: aload         6
     193: getfield      #761                // Field org/eclipse/swt/graphics/Point.x:I
     196: if_icmpge     212
     199: aload         7
     201: getfield      #492                // Field org/eclipse/swt/graphics/Point.y:I
     204: aload         6
     206: getfield      #492                // Field org/eclipse/swt/graphics/Point.y:I
     209: if_icmpeq     225
     212: aload         7
     214: getfield      #492                // Field org/eclipse/swt/graphics/Point.y:I
     217: aload         6
     219: getfield      #492                // Field org/eclipse/swt/graphics/Point.y:I
     222: if_icmpge     234
     225: aload_0
     226: getfield      #142                // Field fProposalShell:Lorg/eclipse/swt/widgets/Shell;
     229: aload         7
     231: invokevirtual #956                // Method org/eclipse/swt/widgets/Shell.setLocation:(Lorg/eclipse/swt/graphics/Point;)V
     234: aload_0
     235: iconst_0
     236: iconst_0
     237: invokevirtual #958                // Method selectProposal:(IZ)V
     240: return

  private org.eclipse.swt.graphics.Point getLocation();
    Code:
       0: aload_0
       1: getfield      #115                // Field fContentAssistSubjectControlAdapter:Lorg/eclipse/jface/text/contentassist/ContentAssistSubjectControlAdapter;
       4: invokevirtual #968                // Method org/eclipse/jface/text/contentassist/ContentAssistSubjectControlAdapter.getCaretOffset:()I
       7: istore_1
       8: aload_0
       9: getfield      #104                // Field fContentAssistant:Lorg/eclipse/jface/text/contentassist/ContentAssistant;
      12: invokevirtual #971                // Method org/eclipse/jface/text/contentassist/ContentAssistant.getLayoutManager:()Lorg/eclipse/jface/text/contentassist/ContentAssistant$LayoutManager;
      15: aload_0
      16: getfield      #142                // Field fProposalShell:Lorg/eclipse/swt/widgets/Shell;
      19: aload_0
      20: getfield      #975                // Field fSize:Lorg/eclipse/swt/graphics/Point;
      23: ifnonnull     36
      26: aload_0
      27: getfield      #142                // Field fProposalShell:Lorg/eclipse/swt/widgets/Shell;
      30: invokevirtual #977                // Method org/eclipse/swt/widgets/Shell.getSize:()Lorg/eclipse/swt/graphics/Point;
      33: goto          40
      36: aload_0
      37: getfield      #975                // Field fSize:Lorg/eclipse/swt/graphics/Point;
      40: iload_1
      41: aload_0
      42: invokevirtual #978                // Method org/eclipse/jface/text/contentassist/ContentAssistant$LayoutManager.computeBoundsBelowAbove:(Lorg/eclipse/swt/widgets/Shell;Lorg/eclipse/swt/graphics/Point;ILorg/eclipse/jface/text/contentassist/CompletionProposalPopup;)Lorg/eclipse/swt/graphics/Rectangle;
      45: astore_2
      46: aload_2
      47: invokestatic  #984                // Method org/eclipse/jface/util/Geometry.getLocation:(Lorg/eclipse/swt/graphics/Rectangle;)Lorg/eclipse/swt/graphics/Point;
      50: areturn

  org.eclipse.swt.graphics.Point getSize();
    Code:
       0: aload_0
       1: getfield      #975                // Field fSize:Lorg/eclipse/swt/graphics/Point;
       4: areturn

  void displayProposals();
    Code:
       0: aload_0
       1: iconst_1
       2: invokevirtual #992                // Method displayProposals:(Z)V
       5: return

  void displayProposals(boolean);
    Code:
       0: aload_0
       1: getfield      #142                // Field fProposalShell:Lorg/eclipse/swt/widgets/Shell;
       4: invokestatic  #144                // Method org/eclipse/jface/util/Util.isValid:(Lorg/eclipse/swt/widgets/Widget;)Z
       7: ifeq          20
      10: aload_0
      11: getfield      #280                // Field fProposalTable:Lorg/eclipse/swt/widgets/Table;
      14: invokestatic  #144                // Method org/eclipse/jface/util/Util.isValid:(Lorg/eclipse/swt/widgets/Widget;)Z
      17: ifne          21
      20: return
      21: aload_0
      22: getfield      #104                // Field fContentAssistant:Lorg/eclipse/jface/text/contentassist/ContentAssistant;
      25: aload_0
      26: iconst_1
      27: invokevirtual #994                // Method org/eclipse/jface/text/contentassist/ContentAssistant.addContentAssistListener:(Lorg/eclipse/jface/text/contentassist/IContentAssistListener;I)Z
      30: ifeq          48
      33: aload_0
      34: invokevirtual #998                // Method ensureDocumentListenerInstalled:()V
      37: iload_1
      38: ifeq          52
      41: aload_0
      42: invokevirtual #1001               // Method configureAndMakeVisible:()V
      45: goto          52
      48: aload_0
      49: invokevirtual #201                // Method hide:()V
      52: return

  private void configureAndMakeVisible();
    Code:
       0: aload_0
       1: getfield      #894                // Field fFocusHelper:Lorg/eclipse/jface/text/IEditingSupport;
       4: ifnonnull     19
       7: aload_0
       8: new           #1005               // class org/eclipse/jface/text/contentassist/CompletionProposalPopup$8
      11: dup
      12: aload_0
      13: invokespecial #1007               // Method org/eclipse/jface/text/contentassist/CompletionProposalPopup$8."<init>":(Lorg/eclipse/jface/text/contentassist/CompletionProposalPopup;)V
      16: putfield      #894                // Field fFocusHelper:Lorg/eclipse/jface/text/IEditingSupport;
      19: aload_0
      20: getfield      #106                // Field fViewer:Lorg/eclipse/jface/text/ITextViewer;
      23: instanceof    #786                // class org/eclipse/jface/text/IEditingSupportRegistry
      26: ifeq          47
      29: aload_0
      30: getfield      #106                // Field fViewer:Lorg/eclipse/jface/text/ITextViewer;
      33: checkcast     #786                // class org/eclipse/jface/text/IEditingSupportRegistry
      36: astore_1
      37: aload_1
      38: aload_0
      39: getfield      #894                // Field fFocusHelper:Lorg/eclipse/jface/text/IEditingSupport;
      42: invokeinterface #788,  2          // InterfaceMethod org/eclipse/jface/text/IEditingSupportRegistry.register:(Lorg/eclipse/jface/text/IEditingSupport;)V
      47: aload_0
      48: getfield      #142                // Field fProposalShell:Lorg/eclipse/swt/widgets/Shell;
      51: iconst_1
      52: invokevirtual #903                // Method org/eclipse/swt/widgets/Shell.setVisible:(Z)V
      55: aload_0
      56: getfield      #115                // Field fContentAssistSubjectControlAdapter:Lorg/eclipse/jface/text/contentassist/ContentAssistSubjectControlAdapter;
      59: invokevirtual #1008               // Method org/eclipse/jface/text/contentassist/ContentAssistSubjectControlAdapter.supportsVerifyKeyListener:()Z
      62: ifne          83
      65: aload_0
      66: getfield      #142                // Field fProposalShell:Lorg/eclipse/swt/widgets/Shell;
      69: invokestatic  #144                // Method org/eclipse/jface/util/Util.isValid:(Lorg/eclipse/swt/widgets/Widget;)Z
      72: ifeq          83
      75: aload_0
      76: getfield      #142                // Field fProposalShell:Lorg/eclipse/swt/widgets/Shell;
      79: invokevirtual #1011               // Method org/eclipse/swt/widgets/Shell.setFocus:()Z
      82: pop
      83: aload_0
      84: getfield      #108                // Field fAdditionalInfoController:Lorg/eclipse/jface/text/contentassist/AdditionalInfoController;
      87: ifnull        118
      90: aload_0
      91: getfield      #280                // Field fProposalTable:Lorg/eclipse/swt/widgets/Table;
      94: invokestatic  #144                // Method org/eclipse/jface/util/Util.isValid:(Lorg/eclipse/swt/widgets/Widget;)Z
      97: ifeq          118
     100: aload_0
     101: getfield      #108                // Field fAdditionalInfoController:Lorg/eclipse/jface/text/contentassist/AdditionalInfoController;
     104: aload_0
     105: getfield      #280                // Field fProposalTable:Lorg/eclipse/swt/widgets/Table;
     108: invokevirtual #1014               // Method org/eclipse/jface/text/contentassist/AdditionalInfoController.install:(Lorg/eclipse/swt/widgets/Control;)V
     111: aload_0
     112: getfield      #108                // Field fAdditionalInfoController:Lorg/eclipse/jface/text/contentassist/AdditionalInfoController;
     115: invokevirtual #1016               // Method org/eclipse/jface/text/contentassist/AdditionalInfoController.handleTableSelectionChanged:()V
     118: return

  void ensureDocumentListenerInstalled();
    Code:
       0: aload_0
       1: getfield      #913                // Field fDocumentListener:Lorg/eclipse/jface/text/IDocumentListener;
       4: ifnonnull     41
       7: aload_0
       8: new           #1019               // class org/eclipse/jface/text/contentassist/CompletionProposalPopup$9
      11: dup
      12: aload_0
      13: invokespecial #1021               // Method org/eclipse/jface/text/contentassist/CompletionProposalPopup$9."<init>":(Lorg/eclipse/jface/text/contentassist/CompletionProposalPopup;)V
      16: putfield      #913                // Field fDocumentListener:Lorg/eclipse/jface/text/IDocumentListener;
      19: aload_0
      20: getfield      #115                // Field fContentAssistSubjectControlAdapter:Lorg/eclipse/jface/text/contentassist/ContentAssistSubjectControlAdapter;
      23: invokevirtual #646                // Method org/eclipse/jface/text/contentassist/ContentAssistSubjectControlAdapter.getDocument:()Lorg/eclipse/jface/text/IDocument;
      26: astore_1
      27: aload_1
      28: ifnull        41
      31: aload_1
      32: aload_0
      33: getfield      #913                // Field fDocumentListener:Lorg/eclipse/jface/text/IDocumentListener;
      36: invokeinterface #1022,  2         // InterfaceMethod org/eclipse/jface/text/IDocument.addDocumentListener:(Lorg/eclipse/jface/text/IDocumentListener;)V
      41: return

  public boolean verifyKey(org.eclipse.swt.events.VerifyEvent);
    Code:
       0: aload_0
       1: getfield      #74                 // Field fInserting:Z
       4: ifeq          9
       7: iconst_0
       8: ireturn
       9: aload_0
      10: getfield      #142                // Field fProposalShell:Lorg/eclipse/swt/widgets/Shell;
      13: invokestatic  #144                // Method org/eclipse/jface/util/Util.isValid:(Lorg/eclipse/swt/widgets/Widget;)Z
      16: ifne          21
      19: iconst_1
      20: ireturn
      21: aload_1
      22: getfield      #1027               // Field org/eclipse/swt/events/VerifyEvent.character:C
      25: istore_2
      26: iload_2
      27: ifne          287
      30: aload_0
      31: getfield      #280                // Field fProposalTable:Lorg/eclipse/swt/widgets/Table;
      34: invokevirtual #751                // Method org/eclipse/swt/widgets/Table.getSelectionIndex:()I
      37: istore_3
      38: aload_0
      39: getfield      #280                // Field fProposalTable:Lorg/eclipse/swt/widgets/Table;
      42: invokevirtual #1032               // Method org/eclipse/swt/widgets/Table.getSize:()Lorg/eclipse/swt/graphics/Point;
      45: getfield      #492                // Field org/eclipse/swt/graphics/Point.y:I
      48: aload_0
      49: getfield      #280                // Field fProposalTable:Lorg/eclipse/swt/widgets/Table;
      52: invokevirtual #348                // Method org/eclipse/swt/widgets/Table.getItemHeight:()I
      55: idiv
      56: iconst_1
      57: isub
      58: istore        4
      60: aload_0
      61: getfield      #280                // Field fProposalTable:Lorg/eclipse/swt/widgets/Table;
      64: invokevirtual #1033               // Method org/eclipse/swt/widgets/Table.getItemCount:()I
      67: istore        5
      69: aload_1
      70: getfield      #1036               // Field org/eclipse/swt/events/VerifyEvent.keyCode:I
      73: tableswitch   { // 16777217 to 16777224

              16777217: 126

              16777218: 141

              16777219: 120

              16777220: 120

              16777221: 176

              16777222: 157

              16777223: 190

              16777224: 195
               default: 203
          }
     120: aload_0
     121: invokevirtual #1039               // Method filterProposals:()V
     124: iconst_1
     125: ireturn
     126: iinc          3, -1
     129: iload_3
     130: ifge          259
     133: iload         5
     135: iconst_1
     136: isub
     137: istore_3
     138: goto          259
     141: iinc          3, 1
     144: iload_3
     145: iload         5
     147: iconst_1
     148: isub
     149: if_icmple     259
     152: iconst_0
     153: istore_3
     154: goto          259
     157: iload_3
     158: iload         4
     160: iadd
     161: istore_3
     162: iload_3
     163: iload         5
     165: if_icmplt     259
     168: iload         5
     170: iconst_1
     171: isub
     172: istore_3
     173: goto          259
     176: iload_3
     177: iload         4
     179: isub
     180: istore_3
     181: iload_3
     182: ifge          259
     185: iconst_0
     186: istore_3
     187: goto          259
     190: iconst_0
     191: istore_3
     192: goto          259
     195: iload         5
     197: iconst_1
     198: isub
     199: istore_3
     200: goto          259
     203: aload_1
     204: getfield      #1036               // Field org/eclipse/swt/events/VerifyEvent.keyCode:I
     207: ldc_w         #1042               // int 16777298
     210: if_icmpeq     257
     213: aload_1
     214: getfield      #1036               // Field org/eclipse/swt/events/VerifyEvent.keyCode:I
     217: getstatic     #1043               // Field org/eclipse/swt/SWT.MOD1:I
     220: if_icmpeq     257
     223: aload_1
     224: getfield      #1036               // Field org/eclipse/swt/events/VerifyEvent.keyCode:I
     227: getstatic     #1048               // Field org/eclipse/swt/SWT.MOD2:I
     230: if_icmpeq     257
     233: aload_1
     234: getfield      #1036               // Field org/eclipse/swt/events/VerifyEvent.keyCode:I
     237: getstatic     #1051               // Field org/eclipse/swt/SWT.MOD3:I
     240: if_icmpeq     257
     243: aload_1
     244: getfield      #1036               // Field org/eclipse/swt/events/VerifyEvent.keyCode:I
     247: getstatic     #1054               // Field org/eclipse/swt/SWT.MOD4:I
     250: if_icmpeq     257
     253: aload_0
     254: invokevirtual #201                // Method hide:()V
     257: iconst_1
     258: ireturn
     259: aload_0
     260: iload_3
     261: aload_1
     262: getfield      #1057               // Field org/eclipse/swt/events/VerifyEvent.stateMask:I
     265: ldc_w         #1059               // int 262144
     268: iand
     269: ifeq          276
     272: iconst_1
     273: goto          277
     276: iconst_0
     277: invokevirtual #958                // Method selectProposal:(IZ)V
     280: aload_1
     281: iconst_0
     282: putfield      #1060               // Field org/eclipse/swt/events/VerifyEvent.doit:Z
     285: iconst_0
     286: ireturn
     287: iload_2
     288: lookupswitch  { // 5

                     8: 383

                     9: 368

                    10: 352

                    13: 352

                    27: 340
               default: 424
          }
     340: aload_1
     341: iconst_0
     342: putfield      #1060               // Field org/eclipse/swt/events/VerifyEvent.doit:Z
     345: aload_0
     346: invokevirtual #201                // Method hide:()V
     349: goto          500
     352: aload_1
     353: iconst_0
     354: putfield      #1060               // Field org/eclipse/swt/events/VerifyEvent.doit:Z
     357: aload_0
     358: aload_1
     359: getfield      #1057               // Field org/eclipse/swt/events/VerifyEvent.stateMask:I
     362: invokevirtual #1063               // Method insertSelectedProposalWithMask:(I)V
     365: goto          500
     368: aload_1
     369: iconst_0
     370: putfield      #1060               // Field org/eclipse/swt/events/VerifyEvent.doit:Z
     373: aload_0
     374: getfield      #142                // Field fProposalShell:Lorg/eclipse/swt/widgets/Shell;
     377: invokevirtual #1011               // Method org/eclipse/swt/widgets/Shell.setFocus:()Z
     380: pop
     381: iconst_0
     382: ireturn
     383: aload_0
     384: getfield      #174                // Field fFilterOffset:I
     387: ifle          500
     390: aload_0
     391: getfield      #115                // Field fContentAssistSubjectControlAdapter:Lorg/eclipse/jface/text/contentassist/ContentAssistSubjectControlAdapter;
     394: invokevirtual #646                // Method org/eclipse/jface/text/contentassist/ContentAssistSubjectControlAdapter.getDocument:()Lorg/eclipse/jface/text/IDocument;
     397: aload_0
     398: getfield      #174                // Field fFilterOffset:I
     401: iconst_1
     402: isub
     403: invokeinterface #1065,  2         // InterfaceMethod org/eclipse/jface/text/IDocument.getChar:(I)C
     408: bipush        32
     410: if_icmpne     500
     413: aload_0
     414: invokevirtual #201                // Method hide:()V
     417: goto          500
     420: pop
     421: goto          500
     424: aload_0
     425: getfield      #104                // Field fContentAssistant:Lorg/eclipse/jface/text/contentassist/ContentAssistant;
     428: invokevirtual #1069               // Method org/eclipse/jface/text/contentassist/ContentAssistant.isCompletionProposalTriggerCharsEnabled:()Z
     431: ifeq          500
     434: aload_0
     435: invokevirtual #756                // Method getSelectedProposal:()Lorg/eclipse/jface/text/contentassist/ICompletionProposal;
     438: astore_3
     439: aload_3
     440: instanceof    #798                // class org/eclipse/jface/text/contentassist/ICompletionProposalExtension
     443: ifeq          500
     446: aload_3
     447: checkcast     #798                // class org/eclipse/jface/text/contentassist/ICompletionProposalExtension
     450: astore        4
     452: aload         4
     454: invokeinterface #1072,  1         // InterfaceMethod org/eclipse/jface/text/contentassist/ICompletionProposalExtension.getTriggerCharacters:()[C
     459: astore        5
     461: aload_0
     462: aload         5
     464: iload_2
     465: invokevirtual #1076               // Method contains:([CC)Z
     468: ifeq          500
     471: aload_1
     472: iconst_0
     473: putfield      #1060               // Field org/eclipse/swt/events/VerifyEvent.doit:Z
     476: aload_0
     477: invokevirtual #201                // Method hide:()V
     480: aload_0
     481: aload_3
     482: iload_2
     483: aload_1
     484: getfield      #1057               // Field org/eclipse/swt/events/VerifyEvent.stateMask:I
     487: aload_0
     488: getfield      #115                // Field fContentAssistSubjectControlAdapter:Lorg/eclipse/jface/text/contentassist/ContentAssistSubjectControlAdapter;
     491: invokevirtual #758                // Method org/eclipse/jface/text/contentassist/ContentAssistSubjectControlAdapter.getSelectedRange:()Lorg/eclipse/swt/graphics/Point;
     494: getfield      #761                // Field org/eclipse/swt/graphics/Point.x:I
     497: invokevirtual #764                // Method insertProposal:(Lorg/eclipse/jface/text/contentassist/ICompletionProposal;CII)V
     500: iconst_1
     501: ireturn
    Exception table:
       from    to  target type
         383   417   420   Class org/eclipse/jface/text/BadLocationException

  private void selectProposal(int, boolean);
    Code:
       0: aload_0
       1: invokevirtual #756                // Method getSelectedProposal:()Lorg/eclipse/jface/text/contentassist/ICompletionProposal;
       4: astore_3
       5: aload_3
       6: instanceof    #792                // class org/eclipse/jface/text/contentassist/ICompletionProposalExtension2
       9: ifeq          32
      12: aload_0
      13: getfield      #106                // Field fViewer:Lorg/eclipse/jface/text/ITextViewer;
      16: ifnull        32
      19: aload_3
      20: checkcast     #792                // class org/eclipse/jface/text/contentassist/ICompletionProposalExtension2
      23: aload_0
      24: getfield      #106                // Field fViewer:Lorg/eclipse/jface/text/ITextViewer;
      27: invokeinterface #927,  2          // InterfaceMethod org/eclipse/jface/text/contentassist/ICompletionProposalExtension2.unselected:(Lorg/eclipse/jface/text/ITextViewer;)V
      32: aload_0
      33: getfield      #622                // Field fFilteredProposals:Ljava/util/List;
      36: astore        4
      38: aload         4
      40: ifnull        54
      43: iload_1
      44: aload         4
      46: invokeinterface #624,  1          // InterfaceMethod java/util/List.size:()I
      51: if_icmplt     61
      54: aload_0
      55: aconst_null
      56: iload_2
      57: invokevirtual #1090               // Method fireSelectionEvent:(Lorg/eclipse/jface/text/contentassist/ICompletionProposal;Z)V
      60: return
      61: aload         4
      63: iload_1
      64: invokeinterface #626,  2          // InterfaceMethod java/util/List.get:(I)Ljava/lang/Object;
      69: checkcast     #629                // class org/eclipse/jface/text/contentassist/ICompletionProposal
      72: astore        5
      74: aload         5
      76: instanceof    #792                // class org/eclipse/jface/text/contentassist/ICompletionProposalExtension2
      79: ifeq          104
      82: aload_0
      83: getfield      #106                // Field fViewer:Lorg/eclipse/jface/text/ITextViewer;
      86: ifnull        104
      89: aload         5
      91: checkcast     #792                // class org/eclipse/jface/text/contentassist/ICompletionProposalExtension2
      94: aload_0
      95: getfield      #106                // Field fViewer:Lorg/eclipse/jface/text/ITextViewer;
      98: iload_2
      99: invokeinterface #1094,  3         // InterfaceMethod org/eclipse/jface/text/contentassist/ICompletionProposalExtension2.selected:(Lorg/eclipse/jface/text/ITextViewer;Z)V
     104: aload_0
     105: aload         5
     107: iload_2
     108: invokevirtual #1090               // Method fireSelectionEvent:(Lorg/eclipse/jface/text/contentassist/ICompletionProposal;Z)V
     111: aload_0
     112: aload         5
     114: putfield      #925                // Field fLastProposal:Lorg/eclipse/jface/text/contentassist/ICompletionProposal;
     117: aload_0
     118: getfield      #280                // Field fProposalTable:Lorg/eclipse/swt/widgets/Table;
     121: iload_1
     122: invokevirtual #1098               // Method org/eclipse/swt/widgets/Table.setSelection:(I)V
     125: aload_0
     126: getfield      #280                // Field fProposalTable:Lorg/eclipse/swt/widgets/Table;
     129: invokevirtual #1101               // Method org/eclipse/swt/widgets/Table.showSelection:()V
     132: aload_0
     133: getfield      #108                // Field fAdditionalInfoController:Lorg/eclipse/jface/text/contentassist/AdditionalInfoController;
     136: ifnull        146
     139: aload_0
     140: getfield      #108                // Field fAdditionalInfoController:Lorg/eclipse/jface/text/contentassist/AdditionalInfoController;
     143: invokevirtual #1016               // Method org/eclipse/jface/text/contentassist/AdditionalInfoController.handleTableSelectionChanged:()V
     146: return

  private void fireSelectionEvent(org.eclipse.jface.text.contentassist.ICompletionProposal, boolean);
    Code:
       0: aload_0
       1: getfield      #104                // Field fContentAssistant:Lorg/eclipse/jface/text/contentassist/ContentAssistant;
       4: aload_1
       5: iload_2
       6: invokevirtual #1106               // Method org/eclipse/jface/text/contentassist/ContentAssistant.fireSelectionEvent:(Lorg/eclipse/jface/text/contentassist/ICompletionProposal;Z)V
       9: return

  private void fireAppliedEvent(org.eclipse.jface.text.contentassist.ICompletionProposal);
    Code:
       0: aload_0
       1: getfield      #104                // Field fContentAssistant:Lorg/eclipse/jface/text/contentassist/ContentAssistant;
       4: aload_1
       5: invokevirtual #1107               // Method org/eclipse/jface/text/contentassist/ContentAssistant.fireAppliedEvent:(Lorg/eclipse/jface/text/contentassist/ICompletionProposal;)V
       8: return

  private boolean contains(char[], char);
    Code:
       0: aload_1
       1: ifnonnull     6
       4: iconst_0
       5: ireturn
       6: aload_1
       7: dup
       8: astore        6
      10: arraylength
      11: istore        5
      13: iconst_0
      14: istore        4
      16: goto          35
      19: aload         6
      21: iload         4
      23: caload
      24: istore_3
      25: iload_2
      26: iload_3
      27: if_icmpne     32
      30: iconst_1
      31: ireturn
      32: iinc          4, 1
      35: iload         4
      37: iload         5
      39: if_icmplt     19
      42: iconst_0
      43: ireturn

  public void processEvent(org.eclipse.swt.events.VerifyEvent);
    Code:
       0: return

  void filterProposals();
    Code:
       0: aload_0
       1: getfield      #93                 // Field fIsFilterPending:Ljava/util/concurrent/atomic/AtomicBoolean;
       4: iconst_0
       5: iconst_1
       6: invokevirtual #1112               // Method java/util/concurrent/atomic/AtomicBoolean.compareAndSet:(ZZ)Z
       9: ifeq          31
      12: aload_0
      13: getfield      #115                // Field fContentAssistSubjectControlAdapter:Lorg/eclipse/jface/text/contentassist/ContentAssistSubjectControlAdapter;
      16: invokevirtual #138                // Method org/eclipse/jface/text/contentassist/ContentAssistSubjectControlAdapter.getControl:()Lorg/eclipse/swt/widgets/Control;
      19: astore_1
      20: aload_1
      21: invokevirtual #160                // Method org/eclipse/swt/widgets/Control.getDisplay:()Lorg/eclipse/swt/widgets/Display;
      24: aload_0
      25: getfield      #86                 // Field fFilterRunnable:Ljava/lang/Runnable;
      28: invokevirtual #1116               // Method org/eclipse/swt/widgets/Display.asyncExec:(Ljava/lang/Runnable;)V
      31: return

  java.util.List<org.eclipse.jface.text.contentassist.ICompletionProposal> computeFilteredProposals(int, org.eclipse.jface.text.DocumentEvent);
    Code:
       0: aload_0
       1: getfield      #79                 // Field fDocumentEvents:Ljava/util/List;
       4: invokeinterface #919,  1          // InterfaceMethod java/util/List.clear:()V
       9: iload_1
      10: aload_0
      11: getfield      #1123               // Field fInvocationOffset:I
      14: if_icmpne     31
      17: aload_2
      18: ifnonnull     31
      21: aload_0
      22: iconst_0
      23: putfield      #1125               // Field fIsFilteredSubset:Z
      26: aload_0
      27: getfield      #211                // Field fComputedProposals:Ljava/util/List;
      30: areturn
      31: iload_1
      32: aload_0
      33: getfield      #1123               // Field fInvocationOffset:I
      36: if_icmpge     73
      39: aload_0
      40: iconst_0
      41: putfield      #1125               // Field fIsFilteredSubset:Z
      44: aload_0
      45: iload_1
      46: putfield      #1123               // Field fInvocationOffset:I
      49: aload_0
      50: getfield      #104                // Field fContentAssistant:Lorg/eclipse/jface/text/contentassist/ContentAssistant;
      53: invokevirtual #1127               // Method org/eclipse/jface/text/contentassist/ContentAssistant.fireSessionRestartEvent:()V
      56: aload_0
      57: aload_0
      58: aload_0
      59: getfield      #1123               // Field fInvocationOffset:I
      62: invokevirtual #207                // Method computeProposals:(I)Ljava/util/List;
      65: putfield      #211                // Field fComputedProposals:Ljava/util/List;
      68: aload_0
      69: getfield      #211                // Field fComputedProposals:Ljava/util/List;
      72: areturn
      73: iload_1
      74: aload_0
      75: getfield      #174                // Field fFilterOffset:I
      78: if_icmpge     94
      81: aload_0
      82: getfield      #211                // Field fComputedProposals:Ljava/util/List;
      85: astore_3
      86: aload_0
      87: iconst_0
      88: putfield      #1125               // Field fIsFilteredSubset:Z
      91: goto          104
      94: aload_0
      95: getfield      #622                // Field fFilteredProposals:Ljava/util/List;
      98: astore_3
      99: aload_0
     100: iconst_1
     101: putfield      #1125               // Field fIsFilteredSubset:Z
     104: aload_3
     105: ifnonnull     115
     108: aload_0
     109: iconst_0
     110: putfield      #1125               // Field fIsFilteredSubset:Z
     113: aconst_null
     114: areturn
     115: aload_0
     116: getfield      #115                // Field fContentAssistSubjectControlAdapter:Lorg/eclipse/jface/text/contentassist/ContentAssistSubjectControlAdapter;
     119: invokevirtual #646                // Method org/eclipse/jface/text/contentassist/ContentAssistSubjectControlAdapter.getDocument:()Lorg/eclipse/jface/text/IDocument;
     122: astore        4
     124: aload_3
     125: invokeinterface #624,  1          // InterfaceMethod java/util/List.size:()I
     130: istore        5
     132: new           #76                 // class java/util/ArrayList
     135: dup
     136: iload         5
     138: invokespecial #1130               // Method java/util/ArrayList."<init>":(I)V
     141: astore        6
     143: aload_3
     144: invokeinterface #1131,  1         // InterfaceMethod java/util/List.iterator:()Ljava/util/Iterator;
     149: astore        8
     151: goto          291
     154: aload         8
     156: invokeinterface #1135,  1         // InterfaceMethod java/util/Iterator.next:()Ljava/lang/Object;
     161: checkcast     #629                // class org/eclipse/jface/text/contentassist/ICompletionProposal
     164: astore        7
     166: aload         7
     168: instanceof    #792                // class org/eclipse/jface/text/contentassist/ICompletionProposalExtension2
     171: ifeq          212
     174: aload         7
     176: checkcast     #792                // class org/eclipse/jface/text/contentassist/ICompletionProposalExtension2
     179: astore        9
     181: aload         9
     183: aload         4
     185: iload_1
     186: aload_2
     187: invokeinterface #1141,  4         // InterfaceMethod org/eclipse/jface/text/contentassist/ICompletionProposalExtension2.validate:(Lorg/eclipse/jface/text/IDocument;ILorg/eclipse/jface/text/DocumentEvent;)Z
     192: ifeq          291
     195: aload         6
     197: aload         7
     199: invokeinterface #1145,  2         // InterfaceMethod java/util/List.add:(Ljava/lang/Object;)Z
     204: pop
     205: goto          291
     208: pop
     209: goto          291
     212: aload         7
     214: instanceof    #798                // class org/eclipse/jface/text/contentassist/ICompletionProposalExtension
     217: ifeq          257
     220: aload         7
     222: checkcast     #798                // class org/eclipse/jface/text/contentassist/ICompletionProposalExtension
     225: astore        9
     227: aload         9
     229: aload         4
     231: iload_1
     232: invokeinterface #1149,  3         // InterfaceMethod org/eclipse/jface/text/contentassist/ICompletionProposalExtension.isValidFor:(Lorg/eclipse/jface/text/IDocument;I)Z
     237: ifeq          291
     240: aload         6
     242: aload         7
     244: invokeinterface #1145,  2         // InterfaceMethod java/util/List.add:(Ljava/lang/Object;)Z
     249: pop
     250: goto          291
     253: pop
     254: goto          291
     257: aload_0
     258: iconst_0
     259: putfield      #1125               // Field fIsFilteredSubset:Z
     262: aload_0
     263: iload_1
     264: putfield      #1123               // Field fInvocationOffset:I
     267: aload_0
     268: getfield      #104                // Field fContentAssistant:Lorg/eclipse/jface/text/contentassist/ContentAssistant;
     271: invokevirtual #1127               // Method org/eclipse/jface/text/contentassist/ContentAssistant.fireSessionRestartEvent:()V
     274: aload_0
     275: aload_0
     276: aload_0
     277: getfield      #1123               // Field fInvocationOffset:I
     280: invokevirtual #207                // Method computeProposals:(I)Ljava/util/List;
     283: putfield      #211                // Field fComputedProposals:Ljava/util/List;
     286: aload_0
     287: getfield      #211                // Field fComputedProposals:Ljava/util/List;
     290: areturn
     291: aload         8
     293: invokeinterface #1153,  1         // InterfaceMethod java/util/Iterator.hasNext:()Z
     298: ifne          154
     301: aload         6
     303: areturn
    Exception table:
       from    to  target type
         181   205   208   Class java/lang/RuntimeException
         227   250   253   Class java/lang/RuntimeException

  public void setFocus();
    Code:
       0: aload_0
       1: getfield      #142                // Field fProposalShell:Lorg/eclipse/swt/widgets/Shell;
       4: invokestatic  #144                // Method org/eclipse/jface/util/Util.isValid:(Lorg/eclipse/swt/widgets/Widget;)Z
       7: ifeq          18
      10: aload_0
      11: getfield      #142                // Field fProposalShell:Lorg/eclipse/swt/widgets/Shell;
      14: invokevirtual #1011               // Method org/eclipse/swt/widgets/Shell.setFocus:()Z
      17: pop
      18: return

  boolean canAutoInsert(org.eclipse.jface.text.contentassist.ICompletionProposal);
    Code:
       0: aload_0
       1: getfield      #104                // Field fContentAssistant:Lorg/eclipse/jface/text/contentassist/ContentAssistant;
       4: invokevirtual #1163               // Method org/eclipse/jface/text/contentassist/ContentAssistant.isAutoInserting:()Z
       7: ifeq          31
      10: aload_1
      11: instanceof    #1166               // class org/eclipse/jface/text/contentassist/ICompletionProposalExtension4
      14: ifeq          29
      17: aload_1
      18: checkcast     #1166               // class org/eclipse/jface/text/contentassist/ICompletionProposalExtension4
      21: astore_2
      22: aload_2
      23: invokeinterface #1168,  1         // InterfaceMethod org/eclipse/jface/text/contentassist/ICompletionProposalExtension4.isAutoInsertable:()Z
      28: ireturn
      29: iconst_1
      30: ireturn
      31: iconst_0
      32: ireturn

  public java.lang.String incrementalComplete();
    Code:
       0: aload_0
       1: getfield      #142                // Field fProposalShell:Lorg/eclipse/swt/widgets/Shell;
       4: invokestatic  #144                // Method org/eclipse/jface/util/Util.isValid:(Lorg/eclipse/swt/widgets/Widget;)Z
       7: ifeq          51
      10: aload_0
      11: getfield      #622                // Field fFilteredProposals:Ljava/util/List;
      14: ifnull        51
      17: aload_0
      18: getfield      #176                // Field fLastCompletionOffset:I
      21: aload_0
      22: getfield      #174                // Field fFilterOffset:I
      25: if_icmpne     35
      28: aload_0
      29: invokevirtual #178                // Method handleRepeatedInvocation:()V
      32: goto          119
      35: aload_0
      36: aload_0
      37: getfield      #174                // Field fFilterOffset:I
      40: putfield      #176                // Field fLastCompletionOffset:I
      43: aload_0
      44: invokevirtual #1174               // Method completeCommonPrefix:()Z
      47: pop
      48: goto          119
      51: aload_0
      52: getfield      #115                // Field fContentAssistSubjectControlAdapter:Lorg/eclipse/jface/text/contentassist/ContentAssistSubjectControlAdapter;
      55: invokevirtual #138                // Method org/eclipse/jface/text/contentassist/ContentAssistSubjectControlAdapter.getControl:()Lorg/eclipse/swt/widgets/Control;
      58: astore_1
      59: aload_0
      60: getfield      #133                // Field fKeyListener:Lorg/eclipse/jface/text/contentassist/CompletionProposalPopup$ProposalSelectionListener;
      63: ifnonnull     78
      66: aload_0
      67: new           #135                // class org/eclipse/jface/text/contentassist/CompletionProposalPopup$ProposalSelectionListener
      70: dup
      71: aload_0
      72: invokespecial #137                // Method org/eclipse/jface/text/contentassist/CompletionProposalPopup$ProposalSelectionListener."<init>":(Lorg/eclipse/jface/text/contentassist/CompletionProposalPopup;)V
      75: putfield      #133                // Field fKeyListener:Lorg/eclipse/jface/text/contentassist/CompletionProposalPopup$ProposalSelectionListener;
      78: aload_0
      79: getfield      #142                // Field fProposalShell:Lorg/eclipse/swt/widgets/Shell;
      82: invokestatic  #144                // Method org/eclipse/jface/util/Util.isValid:(Lorg/eclipse/swt/widgets/Widget;)Z
      85: ifne          106
      88: aload_1
      89: invokevirtual #150                // Method org/eclipse/swt/widgets/Control.isDisposed:()Z
      92: ifne          106
      95: aload_0
      96: getfield      #115                // Field fContentAssistSubjectControlAdapter:Lorg/eclipse/jface/text/contentassist/ContentAssistSubjectControlAdapter;
      99: aload_0
     100: getfield      #133                // Field fKeyListener:Lorg/eclipse/jface/text/contentassist/CompletionProposalPopup$ProposalSelectionListener;
     103: invokevirtual #156                // Method org/eclipse/jface/text/contentassist/ContentAssistSubjectControlAdapter.addKeyListener:(Lorg/eclipse/swt/events/KeyListener;)V
     106: aload_1
     107: invokevirtual #160                // Method org/eclipse/swt/widgets/Control.getDisplay:()Lorg/eclipse/swt/widgets/Display;
     110: aload_0
     111: invokedynamic #1177,  0           // InvokeDynamic #4:run:(Lorg/eclipse/jface/text/contentassist/CompletionProposalPopup;)Ljava/lang/Runnable;
     116: invokestatic  #168                // Method org/eclipse/swt/custom/BusyIndicator.showWhile:(Lorg/eclipse/swt/widgets/Display;Ljava/lang/Runnable;)V
     119: aload_0
     120: invokevirtual #181                // Method getErrorMessage:()Ljava/lang/String;
     123: areturn

  boolean completeCommonPrefix();
    Code:
       0: aload_0
       1: getfield      #622                // Field fFilteredProposals:Ljava/util/List;
       4: invokeinterface #624,  1          // InterfaceMethod java/util/List.size:()I
       9: iconst_1
      10: if_icmpne     64
      13: aload_0
      14: aload_0
      15: getfield      #622                // Field fFilteredProposals:Ljava/util/List;
      18: iconst_0
      19: invokeinterface #626,  2          // InterfaceMethod java/util/List.get:(I)Ljava/lang/Object;
      24: checkcast     #629                // class org/eclipse/jface/text/contentassist/ICompletionProposal
      27: invokevirtual #1180               // Method canAutoInsert:(Lorg/eclipse/jface/text/contentassist/ICompletionProposal;)Z
      30: ifeq          62
      33: aload_0
      34: aload_0
      35: getfield      #622                // Field fFilteredProposals:Ljava/util/List;
      38: iconst_0
      39: invokeinterface #626,  2          // InterfaceMethod java/util/List.get:(I)Ljava/lang/Object;
      44: checkcast     #629                // class org/eclipse/jface/text/contentassist/ICompletionProposal
      47: iconst_0
      48: iconst_0
      49: aload_0
      50: getfield      #174                // Field fFilterOffset:I
      53: invokevirtual #764                // Method insertProposal:(Lorg/eclipse/jface/text/contentassist/ICompletionProposal;CII)V
      56: aload_0
      57: invokevirtual #201                // Method hide:()V
      60: iconst_1
      61: ireturn
      62: iconst_0
      63: ireturn
      64: aload_0
      65: getfield      #115                // Field fContentAssistSubjectControlAdapter:Lorg/eclipse/jface/text/contentassist/ContentAssistSubjectControlAdapter;
      68: invokevirtual #646                // Method org/eclipse/jface/text/contentassist/ContentAssistSubjectControlAdapter.getDocument:()Lorg/eclipse/jface/text/IDocument;
      71: astore_1
      72: aconst_null
      73: astore_2
      74: new           #76                 // class java/util/ArrayList
      77: dup
      78: invokespecial #78                 // Method java/util/ArrayList."<init>":()V
      81: astore_3
      82: iconst_0
      83: istore        4
      85: aconst_null
      86: astore        5
      88: iconst_0
      89: istore        6
      91: aconst_null
      92: astore        7
      94: new           #76                 // class java/util/ArrayList
      97: dup
      98: invokespecial #78                 // Method java/util/ArrayList."<init>":()V
     101: astore        8
     103: aload_0
     104: invokevirtual #1182               // Method hasMixedProposals:()Z
     107: istore        9
     109: iconst_0
     110: istore        10
     112: goto          623
     115: aload_0
     116: getfield      #622                // Field fFilteredProposals:Ljava/util/List;
     119: iload         10
     121: invokeinterface #626,  2          // InterfaceMethod java/util/List.get:(I)Ljava/lang/Object;
     126: checkcast     #629                // class org/eclipse/jface/text/contentassist/ICompletionProposal
     129: astore        11
     131: aload         11
     133: instanceof    #1185               // class org/eclipse/jface/text/contentassist/ICompletionProposalExtension3
     136: ifne          141
     139: iconst_0
     140: ireturn
     141: aload         11
     143: checkcast     #1185               // class org/eclipse/jface/text/contentassist/ICompletionProposalExtension3
     146: aload_1
     147: aload_0
     148: getfield      #174                // Field fFilterOffset:I
     151: invokeinterface #1187,  3         // InterfaceMethod org/eclipse/jface/text/contentassist/ICompletionProposalExtension3.getPrefixCompletionStart:(Lorg/eclipse/jface/text/IDocument;I)I
     156: istore        12
     158: aload         11
     160: checkcast     #1185               // class org/eclipse/jface/text/contentassist/ICompletionProposalExtension3
     163: aload_1
     164: aload_0
     165: getfield      #174                // Field fFilterOffset:I
     168: invokeinterface #1191,  3         // InterfaceMethod org/eclipse/jface/text/contentassist/ICompletionProposalExtension3.getPrefixCompletionText:(Lorg/eclipse/jface/text/IDocument;I)Ljava/lang/CharSequence;
     173: astore        13
     175: aload         13
     177: ifnonnull     192
     180: aload         11
     182: invokeinterface #668,  1          // InterfaceMethod org/eclipse/jface/text/contentassist/ICompletionProposal.getDisplayString:()Ljava/lang/String;
     187: invokestatic  #1195               // Method org/eclipse/osgi/util/TextProcessor.deprocess:(Ljava/lang/String;)Ljava/lang/String;
     190: astore        13
     192: aload_0
     193: getfield      #174                // Field fFilterOffset:I
     196: iload         12
     198: isub
     199: istore        14
     201: aload         13
     203: invokeinterface #1200,  1         // InterfaceMethod java/lang/CharSequence.length:()I
     208: iload         14
     210: invokestatic  #373                // Method java/lang/Math.min:(II)I
     213: istore        15
     215: aload_1
     216: iload         12
     218: iload         14
     220: invokeinterface #1204,  3         // InterfaceMethod org/eclipse/jface/text/IDocument.get:(II)Ljava/lang/String;
     225: astore        16
     227: iload         4
     229: ifne          315
     232: aload         13
     234: invokeinterface #1207,  1         // InterfaceMethod java/lang/CharSequence.toString:()Ljava/lang/String;
     239: aload         16
     241: invokevirtual #1210               // Method java/lang/String.startsWith:(Ljava/lang/String;)Z
     244: ifeq          315
     247: iload         9
     249: ifne          315
     252: iconst_0
     253: istore        4
     255: aload_3
     256: aload         11
     258: invokeinterface #1145,  2         // InterfaceMethod java/util/List.add:(Ljava/lang/Object;)Z
     263: pop
     264: aload         13
     266: iload         15
     268: aload         13
     270: invokeinterface #1200,  1         // InterfaceMethod java/lang/CharSequence.length:()I
     275: invokeinterface #1214,  3         // InterfaceMethod java/lang/CharSequence.subSequence:(II)Ljava/lang/CharSequence;
     280: astore        17
     282: aload_2
     283: ifnonnull     304
     286: new           #1218               // class java/lang/StringBuilder
     289: dup
     290: aload         17
     292: invokeinterface #1207,  1         // InterfaceMethod java/lang/CharSequence.toString:()Ljava/lang/String;
     297: invokespecial #1220               // Method java/lang/StringBuilder."<init>":(Ljava/lang/String;)V
     300: astore_2
     301: goto          597
     304: aload_0
     305: aload_2
     306: aload         17
     308: iconst_0
     309: invokevirtual #1222               // Method truncatePostfix:(Ljava/lang/StringBuilder;Ljava/lang/CharSequence;Z)V
     312: goto          597
     315: iload         10
     317: ifeq          325
     320: iload         4
     322: ifeq          592
     325: aload         13
     327: invokeinterface #1207,  1         // InterfaceMethod java/lang/CharSequence.toString:()Ljava/lang/String;
     332: invokevirtual #1226               // Method java/lang/String.toLowerCase:()Ljava/lang/String;
     335: astore        17
     337: aload         16
     339: invokevirtual #1226               // Method java/lang/String.toLowerCase:()Ljava/lang/String;
     342: astore        18
     344: aload         17
     346: aload         18
     348: invokevirtual #1210               // Method java/lang/String.startsWith:(Ljava/lang/String;)Z
     351: ifne          368
     354: aload         17
     356: aload         18
     358: invokevirtual #1229               // Method java/lang/String.contains:(Ljava/lang/CharSequence;)Z
     361: ifeq          368
     364: iconst_1
     365: goto          369
     368: iconst_0
     369: istore        19
     371: iload         19
     373: ifeq          404
     376: aload         17
     378: aload         18
     380: invokevirtual #1232               // Method java/lang/String.indexOf:(Ljava/lang/String;)I
     383: istore        21
     385: aload         13
     387: iload         21
     389: iload         21
     391: iload         15
     393: iadd
     394: invokeinterface #1214,  3         // InterfaceMethod java/lang/CharSequence.subSequence:(II)Ljava/lang/CharSequence;
     399: astore        20
     401: goto          416
     404: aload         13
     406: iconst_0
     407: iload         15
     409: invokeinterface #1214,  3         // InterfaceMethod java/lang/CharSequence.subSequence:(II)Ljava/lang/CharSequence;
     414: astore        20
     416: aload_0
     417: aload         5
     419: iload         6
     421: aload         20
     423: iload         12
     425: aload_1
     426: iload         9
     428: invokevirtual #1235               // Method isPrefixCompatible:(Ljava/lang/CharSequence;ILjava/lang/CharSequence;ILorg/eclipse/jface/text/IDocument;Z)Z
     431: ifeq          590
     434: iconst_1
     435: istore        4
     437: aload         17
     439: invokevirtual #1239               // Method java/lang/String.isEmpty:()Z
     442: ifeq          449
     445: aload         16
     447: astore        20
     449: aload         5
     451: ifnull        479
     454: iload         9
     456: ifeq          479
     459: aload         5
     461: invokeinterface #1207,  1         // InterfaceMethod java/lang/CharSequence.toString:()Ljava/lang/String;
     466: aload         20
     468: invokeinterface #1207,  1         // InterfaceMethod java/lang/CharSequence.toString:()Ljava/lang/String;
     473: invokevirtual #1240               // Method java/lang/String.equalsIgnoreCase:(Ljava/lang/String;)Z
     476: ifne          483
     479: aload         20
     481: astore        5
     483: iload         12
     485: istore        6
     487: iload         19
     489: ifeq          525
     492: aload         17
     494: aload         18
     496: invokevirtual #1232               // Method java/lang/String.indexOf:(Ljava/lang/String;)I
     499: istore        22
     501: aload         13
     503: iload         22
     505: iload         14
     507: iadd
     508: aload         13
     510: invokeinterface #1200,  1         // InterfaceMethod java/lang/CharSequence.length:()I
     515: invokeinterface #1214,  3         // InterfaceMethod java/lang/CharSequence.subSequence:(II)Ljava/lang/CharSequence;
     520: astore        21
     522: goto          543
     525: aload         13
     527: iload         15
     529: aload         13
     531: invokeinterface #1200,  1         // InterfaceMethod java/lang/CharSequence.length:()I
     536: invokeinterface #1214,  3         // InterfaceMethod java/lang/CharSequence.subSequence:(II)Ljava/lang/CharSequence;
     541: astore        21
     543: aload         7
     545: ifnonnull     567
     548: new           #1218               // class java/lang/StringBuilder
     551: dup
     552: aload         21
     554: invokeinterface #1207,  1         // InterfaceMethod java/lang/CharSequence.toString:()Ljava/lang/String;
     559: invokespecial #1220               // Method java/lang/StringBuilder."<init>":(Ljava/lang/String;)V
     562: astore        7
     564: goto          577
     567: aload_0
     568: aload         7
     570: aload         21
     572: iload         9
     574: invokevirtual #1222               // Method truncatePostfix:(Ljava/lang/StringBuilder;Ljava/lang/CharSequence;Z)V
     577: aload         8
     579: aload         11
     581: invokeinterface #1145,  2         // InterfaceMethod java/util/List.add:(Ljava/lang/Object;)Z
     586: pop
     587: goto          597
     590: iconst_0
     591: ireturn
     592: iconst_0
     593: ireturn
     594: pop
     595: iconst_0
     596: ireturn
     597: aload_2
     598: ifnull        620
     601: aload_2
     602: invokevirtual #1243               // Method java/lang/StringBuilder.length:()I
     605: ifne          620
     608: aload_3
     609: invokeinterface #624,  1          // InterfaceMethod java/util/List.size:()I
     614: iconst_1
     615: if_icmple     620
     618: iconst_0
     619: ireturn
     620: iinc          10, 1
     623: iload         10
     625: aload_0
     626: getfield      #622                // Field fFilteredProposals:Ljava/util/List;
     629: invokeinterface #624,  1          // InterfaceMethod java/util/List.size:()I
     634: if_icmplt     115
     637: aload_3
     638: invokeinterface #624,  1          // InterfaceMethod java/util/List.size:()I
     643: iconst_1
     644: if_icmpne     695
     647: aload_3
     648: iconst_0
     649: invokeinterface #626,  2          // InterfaceMethod java/util/List.get:(I)Ljava/lang/Object;
     654: checkcast     #629                // class org/eclipse/jface/text/contentassist/ICompletionProposal
     657: astore        10
     659: aload_0
     660: aload         10
     662: invokevirtual #1180               // Method canAutoInsert:(Lorg/eclipse/jface/text/contentassist/ICompletionProposal;)Z
     665: ifeq          693
     668: aload_2
     669: invokevirtual #1243               // Method java/lang/StringBuilder.length:()I
     672: ifle          693
     675: aload_0
     676: aload         10
     678: iconst_0
     679: iconst_0
     680: aload_0
     681: getfield      #1123               // Field fInvocationOffset:I
     684: invokevirtual #764                // Method insertProposal:(Lorg/eclipse/jface/text/contentassist/ICompletionProposal;CII)V
     687: aload_0
     688: invokevirtual #201                // Method hide:()V
     691: iconst_1
     692: ireturn
     693: iconst_0
     694: ireturn
     695: iload         4
     697: ifeq          753
     700: aload         8
     702: invokeinterface #624,  1          // InterfaceMethod java/util/List.size:()I
     707: iconst_1
     708: if_icmpne     753
     711: aload         8
     713: iconst_0
     714: invokeinterface #626,  2          // InterfaceMethod java/util/List.get:(I)Ljava/lang/Object;
     719: checkcast     #629                // class org/eclipse/jface/text/contentassist/ICompletionProposal
     722: astore        10
     724: aload_0
     725: aload         10
     727: invokevirtual #1180               // Method canAutoInsert:(Lorg/eclipse/jface/text/contentassist/ICompletionProposal;)Z
     730: ifeq          751
     733: aload_0
     734: aload         10
     736: iconst_0
     737: iconst_0
     738: aload_0
     739: getfield      #1123               // Field fInvocationOffset:I
     742: invokevirtual #764                // Method insertProposal:(Lorg/eclipse/jface/text/contentassist/ICompletionProposal;CII)V
     745: aload_0
     746: invokevirtual #201                // Method hide:()V
     749: iconst_1
     750: ireturn
     751: iconst_0
     752: ireturn
     753: iload         4
     755: ifeq          765
     758: aload         5
     760: astore        10
     762: goto          770
     765: ldc_w         #1244               // String
     768: astore        10
     770: iload         4
     772: ifeq          782
     775: aload         7
     777: astore        11
     779: goto          785
     782: aload_2
     783: astore        11
     785: aload         10
     787: ifnull        795
     790: aload         11
     792: ifnonnull     797
     795: iconst_0
     796: ireturn
     797: aload_1
     798: invokeinterface #1246,  1         // InterfaceMethod org/eclipse/jface/text/IDocument.getLength:()I
     803: aload_0
     804: getfield      #174                // Field fFilterOffset:I
     807: aload         11
     809: invokeinterface #1200,  1         // InterfaceMethod java/lang/CharSequence.length:()I
     814: iadd
     815: invokestatic  #373                // Method java/lang/Math.min:(II)I
     818: istore        12
     820: new           #1218               // class java/lang/StringBuilder
     823: dup
     824: aload_1
     825: aload_0
     826: getfield      #174                // Field fFilterOffset:I
     829: iload         12
     831: aload_0
     832: getfield      #174                // Field fFilterOffset:I
     835: isub
     836: invokeinterface #1204,  3         // InterfaceMethod org/eclipse/jface/text/IDocument.get:(II)Ljava/lang/String;
     841: invokespecial #1220               // Method java/lang/StringBuilder."<init>":(Ljava/lang/String;)V
     844: astore        13
     846: aload_0
     847: aload         13
     849: aload         11
     851: iload         9
     853: invokevirtual #1222               // Method truncatePostfix:(Ljava/lang/StringBuilder;Ljava/lang/CharSequence;Z)V
     856: aload_1
     857: aload_0
     858: getfield      #174                // Field fFilterOffset:I
     861: aload         10
     863: invokeinterface #1200,  1         // InterfaceMethod java/lang/CharSequence.length:()I
     868: isub
     869: aload         10
     871: invokeinterface #1200,  1         // InterfaceMethod java/lang/CharSequence.length:()I
     876: aload         13
     878: invokevirtual #1243               // Method java/lang/StringBuilder.length:()I
     881: iadd
     882: aload         10
     884: invokeinterface #1207,  1         // InterfaceMethod java/lang/CharSequence.toString:()Ljava/lang/String;
     889: aload         11
     891: invokeinterface #1207,  1         // InterfaceMethod java/lang/CharSequence.toString:()Ljava/lang/String;
     896: invokedynamic #1249,  0           // InvokeDynamic #5:makeConcatWithConstants:(Ljava/lang/String;Ljava/lang/String;)Ljava/lang/String;
     901: invokeinterface #1252,  4         // InterfaceMethod org/eclipse/jface/text/IDocument.replace:(IILjava/lang/String;)V
     906: aload_0
     907: getfield      #115                // Field fContentAssistSubjectControlAdapter:Lorg/eclipse/jface/text/contentassist/ContentAssistSubjectControlAdapter;
     910: aload_0
     911: getfield      #174                // Field fFilterOffset:I
     914: aload         11
     916: invokeinterface #1200,  1         // InterfaceMethod java/lang/CharSequence.length:()I
     921: iadd
     922: iconst_0
     923: invokevirtual #814                // Method org/eclipse/jface/text/contentassist/ContentAssistSubjectControlAdapter.setSelectedRange:(II)V
     926: aload_0
     927: getfield      #115                // Field fContentAssistSubjectControlAdapter:Lorg/eclipse/jface/text/contentassist/ContentAssistSubjectControlAdapter;
     930: aload_0
     931: getfield      #174                // Field fFilterOffset:I
     934: aload         11
     936: invokeinterface #1200,  1         // InterfaceMethod java/lang/CharSequence.length:()I
     941: iadd
     942: iconst_0
     943: invokevirtual #817                // Method org/eclipse/jface/text/contentassist/ContentAssistSubjectControlAdapter.revealRange:(II)V
     946: aload_0
     947: dup
     948: getfield      #174                // Field fFilterOffset:I
     951: aload         11
     953: invokeinterface #1200,  1         // InterfaceMethod java/lang/CharSequence.length:()I
     958: iadd
     959: putfield      #174                // Field fFilterOffset:I
     962: aload_0
     963: aload_0
     964: getfield      #174                // Field fFilterOffset:I
     967: putfield      #176                // Field fLastCompletionOffset:I
     970: iconst_0
     971: ireturn
     972: pop
     973: iconst_0
     974: ireturn
    Exception table:
       from    to  target type
         192   590   594   Class org/eclipse/jface/text/BadLocationException
         797   970   972   Class org/eclipse/jface/text/BadLocationException

  private boolean hasMixedProposals();
    Code:
       0: aload_0
       1: getfield      #115                // Field fContentAssistSubjectControlAdapter:Lorg/eclipse/jface/text/contentassist/ContentAssistSubjectControlAdapter;
       4: invokevirtual #646                // Method org/eclipse/jface/text/contentassist/ContentAssistSubjectControlAdapter.getDocument:()Lorg/eclipse/jface/text/IDocument;
       7: astore_1
       8: iconst_0
       9: istore_2
      10: iconst_0
      11: istore_3
      12: aload_0
      13: getfield      #622                // Field fFilteredProposals:Ljava/util/List;
      16: invokeinterface #1131,  1         // InterfaceMethod java/util/List.iterator:()Ljava/util/Iterator;
      21: astore        5
      23: goto          192
      26: aload         5
      28: invokeinterface #1135,  1         // InterfaceMethod java/util/Iterator.next:()Ljava/lang/Object;
      33: checkcast     #629                // class org/eclipse/jface/text/contentassist/ICompletionProposal
      36: astore        4
      38: aload         4
      40: instanceof    #1185               // class org/eclipse/jface/text/contentassist/ICompletionProposalExtension3
      43: ifne          48
      46: iconst_0
      47: ireturn
      48: aload         4
      50: checkcast     #1185               // class org/eclipse/jface/text/contentassist/ICompletionProposalExtension3
      53: aload_1
      54: aload_0
      55: getfield      #174                // Field fFilterOffset:I
      58: invokeinterface #1187,  3         // InterfaceMethod org/eclipse/jface/text/contentassist/ICompletionProposalExtension3.getPrefixCompletionStart:(Lorg/eclipse/jface/text/IDocument;I)I
      63: istore        6
      65: aload         4
      67: checkcast     #1185               // class org/eclipse/jface/text/contentassist/ICompletionProposalExtension3
      70: aload_1
      71: aload_0
      72: getfield      #174                // Field fFilterOffset:I
      75: invokeinterface #1191,  3         // InterfaceMethod org/eclipse/jface/text/contentassist/ICompletionProposalExtension3.getPrefixCompletionText:(Lorg/eclipse/jface/text/IDocument;I)Ljava/lang/CharSequence;
      80: astore        7
      82: aload         7
      84: ifnonnull     99
      87: aload         4
      89: invokeinterface #668,  1          // InterfaceMethod org/eclipse/jface/text/contentassist/ICompletionProposal.getDisplayString:()Ljava/lang/String;
      94: invokestatic  #1195               // Method org/eclipse/osgi/util/TextProcessor.deprocess:(Ljava/lang/String;)Ljava/lang/String;
      97: astore        7
      99: aload_0
     100: getfield      #174                // Field fFilterOffset:I
     103: iload         6
     105: isub
     106: istore        8
     108: aload_1
     109: iload         6
     111: iload         8
     113: invokeinterface #1204,  3         // InterfaceMethod org/eclipse/jface/text/IDocument.get:(II)Ljava/lang/String;
     118: astore        9
     120: aload         7
     122: invokeinterface #1207,  1         // InterfaceMethod java/lang/CharSequence.toString:()Ljava/lang/String;
     127: astore        10
     129: aload         10
     131: invokevirtual #1239               // Method java/lang/String.isEmpty:()Z
     134: ifne          153
     137: aload         10
     139: invokevirtual #1226               // Method java/lang/String.toLowerCase:()Ljava/lang/String;
     142: aload         9
     144: invokevirtual #1226               // Method java/lang/String.toLowerCase:()Ljava/lang/String;
     147: invokevirtual #1210               // Method java/lang/String.startsWith:(Ljava/lang/String;)Z
     150: ifeq          158
     153: iconst_1
     154: istore_3
     155: goto          182
     158: aload         10
     160: invokevirtual #1226               // Method java/lang/String.toLowerCase:()Ljava/lang/String;
     163: aload         9
     165: invokevirtual #1226               // Method java/lang/String.toLowerCase:()Ljava/lang/String;
     168: invokevirtual #1229               // Method java/lang/String.contains:(Ljava/lang/CharSequence;)Z
     171: ifeq          182
     174: iconst_1
     175: istore_2
     176: goto          182
     179: pop
     180: iconst_0
     181: ireturn
     182: iload_3
     183: ifeq          192
     186: iload_2
     187: ifeq          192
     190: iconst_1
     191: ireturn
     192: aload         5
     194: invokeinterface #1153,  1         // InterfaceMethod java/util/Iterator.hasNext:()Z
     199: ifne          26
     202: iconst_0
     203: ireturn
    Exception table:
       from    to  target type
         108   176   179   Class org/eclipse/jface/text/BadLocationException

  private boolean isPrefixCompatible(java.lang.CharSequence, int, java.lang.CharSequence, int, org.eclipse.jface.text.IDocument, boolean) throws org.eclipse.jface.text.BadLocationException;
    Code:
       0: aload_1
       1: ifnull        8
       4: aload_3
       5: ifnonnull     10
       8: iconst_1
       9: ireturn
      10: iload_2
      11: iload         4
      13: invokestatic  #373                // Method java/lang/Math.min:(II)I
      16: istore        7
      18: iload_2
      19: aload_1
      20: invokeinterface #1200,  1         // InterfaceMethod java/lang/CharSequence.length:()I
      25: iadd
      26: istore        8
      28: iload         4
      30: aload_3
      31: invokeinterface #1200,  1         // InterfaceMethod java/lang/CharSequence.length:()I
      36: iadd
      37: istore        9
      39: aload         5
      41: iload_2
      42: iload         7
      44: iload_2
      45: isub
      46: invokeinterface #1204,  3         // InterfaceMethod org/eclipse/jface/text/IDocument.get:(II)Ljava/lang/String;
      51: aload_1
      52: invokestatic  #1283               // Method java/lang/String.valueOf:(Ljava/lang/Object;)Ljava/lang/String;
      55: aload         5
      57: iload         8
      59: aload_0
      60: getfield      #174                // Field fFilterOffset:I
      63: aload_0
      64: getfield      #174                // Field fFilterOffset:I
      67: iload         8
      69: isub
      70: invokestatic  #373                // Method java/lang/Math.min:(II)I
      73: invokeinterface #1204,  3         // InterfaceMethod org/eclipse/jface/text/IDocument.get:(II)Ljava/lang/String;
      78: invokedynamic #1287,  0           // InvokeDynamic #6:makeConcatWithConstants:(Ljava/lang/String;Ljava/lang/String;Ljava/lang/String;)Ljava/lang/String;
      83: astore        10
      85: aload         5
      87: iload         4
      89: iload         7
      91: iload         4
      93: isub
      94: invokeinterface #1204,  3         // InterfaceMethod org/eclipse/jface/text/IDocument.get:(II)Ljava/lang/String;
      99: aload_3
     100: invokestatic  #1283               // Method java/lang/String.valueOf:(Ljava/lang/Object;)Ljava/lang/String;
     103: aload         5
     105: iload         9
     107: aload_0
     108: getfield      #174                // Field fFilterOffset:I
     111: aload_0
     112: getfield      #174                // Field fFilterOffset:I
     115: iload         9
     117: isub
     118: invokestatic  #373                // Method java/lang/Math.min:(II)I
     121: invokeinterface #1204,  3         // InterfaceMethod org/eclipse/jface/text/IDocument.get:(II)Ljava/lang/String;
     126: invokedynamic #1290,  0           // InvokeDynamic #7:makeConcatWithConstants:(Ljava/lang/String;Ljava/lang/String;Ljava/lang/String;)Ljava/lang/String;
     131: astore        11
     133: iload         6
     135: ifeq          148
     138: aload         10
     140: aload         11
     142: invokevirtual #1240               // Method java/lang/String.equalsIgnoreCase:(Ljava/lang/String;)Z
     145: goto          155
     148: aload         10
     150: aload         11
     152: invokevirtual #1291               // Method java/lang/String.equals:(Ljava/lang/Object;)Z
     155: ireturn

  private void truncatePostfix(java.lang.StringBuilder, java.lang.CharSequence, boolean);
    Code:
       0: aload_1
       1: invokevirtual #1243               // Method java/lang/StringBuilder.length:()I
       4: aload_2
       5: invokeinterface #1200,  1         // InterfaceMethod java/lang/CharSequence.length:()I
      10: invokestatic  #373                // Method java/lang/Math.min:(II)I
      13: istore        4
      15: iconst_0
      16: istore        5
      18: goto          102
      21: iload_3
      22: ifeq          58
      25: aload_2
      26: iload         5
      28: invokeinterface #1303,  2         // InterfaceMethod java/lang/CharSequence.charAt:(I)C
      33: invokestatic  #1306               // Method java/lang/Character.toUpperCase:(C)C
      36: aload_1
      37: iload         5
      39: invokevirtual #1312               // Method java/lang/StringBuilder.charAt:(I)C
      42: invokestatic  #1306               // Method java/lang/Character.toUpperCase:(C)C
      45: if_icmpne     52
      48: iconst_1
      49: goto          53
      52: iconst_0
      53: istore        6
      55: goto          82
      58: aload_2
      59: iload         5
      61: invokeinterface #1303,  2         // InterfaceMethod java/lang/CharSequence.charAt:(I)C
      66: aload_1
      67: iload         5
      69: invokevirtual #1312               // Method java/lang/StringBuilder.charAt:(I)C
      72: if_icmpne     79
      75: iconst_1
      76: goto          80
      79: iconst_0
      80: istore        6
      82: iload         6
      84: ifne          99
      87: aload_1
      88: iload         5
      90: aload_1
      91: invokevirtual #1243               // Method java/lang/StringBuilder.length:()I
      94: invokevirtual #1313               // Method java/lang/StringBuilder.delete:(II)Ljava/lang/StringBuilder;
      97: pop
      98: return
      99: iinc          5, 1
     102: iload         5
     104: iload         4
     106: if_icmplt     21
     109: aload_1
     110: iload         4
     112: aload_1
     113: invokevirtual #1243               // Method java/lang/StringBuilder.length:()I
     116: invokevirtual #1313               // Method java/lang/StringBuilder.delete:(II)Ljava/lang/StringBuilder;
     119: pop
     120: return

  void setMessage(java.lang.String);
    Code:
       0: aload_1
       1: invokestatic  #1321               // Method org/eclipse/core/runtime/Assert.isNotNull:(Ljava/lang/Object;)V
       4: aload_0
       5: invokevirtual #1326               // Method isActive:()Z
       8: ifeq          41
      11: aload_0
      12: getfield      #485                // Field fMessageText:Lorg/eclipse/swt/widgets/Label;
      15: ifnull        41
      18: aload_0
      19: getfield      #485                // Field fMessageText:Lorg/eclipse/swt/widgets/Label;
      22: invokevirtual #1328               // Method org/eclipse/swt/widgets/Label.isDisposed:()Z
      25: ifne          41
      28: aload_0
      29: getfield      #485                // Field fMessageText:Lorg/eclipse/swt/widgets/Label;
      32: aload_1
      33: invokedynamic #1329,  0           // InvokeDynamic #8:makeConcatWithConstants:(Ljava/lang/String;)Ljava/lang/String;
      38: invokevirtual #555                // Method org/eclipse/swt/widgets/Label.setText:(Ljava/lang/String;)V
      41: return

  void setEmptyMessage(java.lang.String);
    Code:
       0: aload_1
       1: invokestatic  #1321               // Method org/eclipse/core/runtime/Assert.isNotNull:(Ljava/lang/Object;)V
       4: aload_0
       5: aload_1
       6: putfield      #100                // Field fEmptyMessage:Ljava/lang/String;
       9: return

  public void setStatusLineVisible(boolean);
    Code:
       0: aload_0
       1: invokevirtual #1326               // Method isActive:()Z
       4: ifeq          33
       7: iload_1
       8: aload_0
       9: getfield      #485                // Field fMessageText:Lorg/eclipse/swt/widgets/Label;
      12: ifnull        29
      15: aload_0
      16: getfield      #485                // Field fMessageText:Lorg/eclipse/swt/widgets/Label;
      19: invokevirtual #1328               // Method org/eclipse/swt/widgets/Label.isDisposed:()Z
      22: ifne          29
      25: iconst_1
      26: goto          30
      29: iconst_0
      30: if_icmpne     34
      33: return
      34: iload_1
      35: ifeq          45
      38: aload_0
      39: invokevirtual #328                // Method createMessageText:()V
      42: goto          57
      45: aload_0
      46: getfield      #485                // Field fMessageText:Lorg/eclipse/swt/widgets/Label;
      49: invokevirtual #1333               // Method org/eclipse/swt/widgets/Label.dispose:()V
      52: aload_0
      53: aconst_null
      54: putfield      #485                // Field fMessageText:Lorg/eclipse/swt/widgets/Label;
      57: aload_0
      58: getfield      #142                // Field fProposalShell:Lorg/eclipse/swt/widgets/Shell;
      61: invokevirtual #1334               // Method org/eclipse/swt/widgets/Shell.layout:()V
      64: return

  void switchedPositionToAbove(boolean);
    Code:
       0: aload_0
       1: getfield      #108                // Field fAdditionalInfoController:Lorg/eclipse/jface/text/contentassist/AdditionalInfoController;
       4: ifnull        46
       7: aload_0
       8: getfield      #108                // Field fAdditionalInfoController:Lorg/eclipse/jface/text/contentassist/AdditionalInfoController;
      11: iconst_3
      12: anewarray     #1338               // class org/eclipse/jface/text/AbstractInformationControlManager$Anchor
      15: dup
      16: iconst_0
      17: getstatic     #1340               // Field org/eclipse/jface/text/AbstractInformationControlManager.ANCHOR_RIGHT:Lorg/eclipse/jface/text/AbstractInformationControlManager$Anchor;
      20: aastore
      21: dup
      22: iconst_1
      23: getstatic     #1346               // Field org/eclipse/jface/text/AbstractInformationControlManager.ANCHOR_LEFT:Lorg/eclipse/jface/text/AbstractInformationControlManager$Anchor;
      26: aastore
      27: dup
      28: iconst_2
      29: iload_1
      30: ifeq          39
      33: getstatic     #1349               // Field org/eclipse/jface/text/AbstractInformationControlManager.ANCHOR_TOP:Lorg/eclipse/jface/text/AbstractInformationControlManager$Anchor;
      36: goto          42
      39: getstatic     #1352               // Field org/eclipse/jface/text/AbstractInformationControlManager.ANCHOR_BOTTOM:Lorg/eclipse/jface/text/AbstractInformationControlManager$Anchor;
      42: aastore
      43: invokevirtual #1355               // Method org/eclipse/jface/text/contentassist/AdditionalInfoController.setFallbackAnchors:([Lorg/eclipse/jface/text/AbstractInformationControlManager$Anchor;)V
      46: return

  org.eclipse.core.commands.IHandler createProposalSelectionHandler(int);
    Code:
       0: new           #1364               // class org/eclipse/jface/text/contentassist/CompletionProposalPopup$ProposalSelectionHandler
       3: dup
       4: aload_0
       5: iload_1
       6: invokespecial #1366               // Method org/eclipse/jface/text/contentassist/CompletionProposalPopup$ProposalSelectionHandler."<init>":(Lorg/eclipse/jface/text/contentassist/CompletionProposalPopup;I)V
       9: areturn

  public void setSorter(org.eclipse.jface.text.contentassist.ICompletionProposalSorter);
    Code:
       0: aload_0
       1: aload_1
       2: putfield      #237                // Field fSorter:Lorg/eclipse/jface/text/contentassist/ICompletionProposalSorter;
       5: return

  void sortProposals(java.util.List<org.eclipse.jface.text.contentassist.ICompletionProposal>);
    Code:
       0: aload_1
       1: aload_0
       2: getfield      #237                // Field fSorter:Lorg/eclipse/jface/text/contentassist/ICompletionProposalSorter;
       5: dup
       6: invokevirtual #1372               // Method java/lang/Object.getClass:()Ljava/lang/Class;
       9: pop
      10: invokedynamic #1376,  0           // InvokeDynamic #9:compare:(Lorg/eclipse/jface/text/contentassist/ICompletionProposalSorter;)Ljava/util/Comparator;
      15: invokeinterface #1380,  2         // InterfaceMethod java/util/List.sort:(Ljava/util/Comparator;)V
      20: return

  private void lambda$0(boolean);
    Code:
       0: aload_0
       1: aload_0
       2: getfield      #115                // Field fContentAssistSubjectControlAdapter:Lorg/eclipse/jface/text/contentassist/ContentAssistSubjectControlAdapter;
       5: invokevirtual #758                // Method org/eclipse/jface/text/contentassist/ContentAssistSubjectControlAdapter.getSelectedRange:()Lorg/eclipse/swt/graphics/Point;
       8: getfield      #761                // Field org/eclipse/swt/graphics/Point.x:I
      11: putfield      #1123               // Field fInvocationOffset:I
      14: aload_0
      15: aload_0
      16: getfield      #1123               // Field fInvocationOffset:I
      19: putfield      #174                // Field fFilterOffset:I
      22: aload_0
      23: aload_0
      24: getfield      #174                // Field fFilterOffset:I
      27: putfield      #176                // Field fLastCompletionOffset:I
      30: aload_0
      31: aload_0
      32: aload_0
      33: getfield      #1123               // Field fInvocationOffset:I
      36: invokevirtual #207                // Method computeProposals:(I)Ljava/util/List;
      39: putfield      #211                // Field fComputedProposals:Ljava/util/List;
      42: aload_0
      43: getfield      #211                // Field fComputedProposals:Ljava/util/List;
      46: ifnonnull     53
      49: iconst_0
      50: goto          62
      53: aload_0
      54: getfield      #211                // Field fComputedProposals:Ljava/util/List;
      57: invokeinterface #624,  1          // InterfaceMethod java/util/List.size:()I
      62: istore_2
      63: iload_2
      64: ifne          76
      67: aload_0
      68: iload_1
      69: invokevirtual #1385               // Method hideWhenNoProposals:(Z)Z
      72: ifeq          76
      75: return
      76: iload_2
      77: iconst_1
      78: if_icmpne     135
      81: iload_1
      82: ifne          135
      85: aload_0
      86: aload_0
      87: getfield      #211                // Field fComputedProposals:Ljava/util/List;
      90: iconst_0
      91: invokeinterface #626,  2          // InterfaceMethod java/util/List.get:(I)Ljava/lang/Object;
      96: checkcast     #629                // class org/eclipse/jface/text/contentassist/ICompletionProposal
      99: invokevirtual #1180               // Method canAutoInsert:(Lorg/eclipse/jface/text/contentassist/ICompletionProposal;)Z
     102: ifeq          135
     105: aload_0
     106: aload_0
     107: getfield      #211                // Field fComputedProposals:Ljava/util/List;
     110: iconst_0
     111: invokeinterface #626,  2          // InterfaceMethod java/util/List.get:(I)Ljava/lang/Object;
     116: checkcast     #629                // class org/eclipse/jface/text/contentassist/ICompletionProposal
     119: iconst_0
     120: iconst_0
     121: aload_0
     122: getfield      #1123               // Field fInvocationOffset:I
     125: invokevirtual #764                // Method insertProposal:(Lorg/eclipse/jface/text/contentassist/ICompletionProposal;CII)V
     128: aload_0
     129: invokevirtual #201                // Method hide:()V
     132: goto          152
     135: aload_0
     136: invokevirtual #1387               // Method createProposalSelector:()V
     139: aload_0
     140: aload_0
     141: getfield      #211                // Field fComputedProposals:Ljava/util/List;
     144: iconst_0
     145: invokevirtual #213                // Method setProposals:(Ljava/util/List;Z)V
     148: aload_0
     149: invokevirtual #1389               // Method displayProposals:()V
     152: return

  private void lambda$2(org.eclipse.swt.events.DisposeEvent);
    Code:
       0: aload_0
       1: invokevirtual #892                // Method unregister:()V
       4: return

  private void lambda$3();
    Code:
       0: aload_0
       1: aload_0
       2: getfield      #115                // Field fContentAssistSubjectControlAdapter:Lorg/eclipse/jface/text/contentassist/ContentAssistSubjectControlAdapter;
       5: invokevirtual #758                // Method org/eclipse/jface/text/contentassist/ContentAssistSubjectControlAdapter.getSelectedRange:()Lorg/eclipse/swt/graphics/Point;
       8: getfield      #761                // Field org/eclipse/swt/graphics/Point.x:I
      11: putfield      #1123               // Field fInvocationOffset:I
      14: aload_0
      15: aload_0
      16: getfield      #1123               // Field fInvocationOffset:I
      19: putfield      #174                // Field fFilterOffset:I
      22: aload_0
      23: aload_0
      24: getfield      #174                // Field fFilterOffset:I
      27: putfield      #176                // Field fLastCompletionOffset:I
      30: aload_0
      31: aload_0
      32: aload_0
      33: getfield      #1123               // Field fInvocationOffset:I
      36: invokevirtual #207                // Method computeProposals:(I)Ljava/util/List;
      39: putfield      #622                // Field fFilteredProposals:Ljava/util/List;
      42: aload_0
      43: getfield      #622                // Field fFilteredProposals:Ljava/util/List;
      46: astore_1
      47: aload_1
      48: ifnonnull     55
      51: iconst_0
      52: goto          61
      55: aload_1
      56: invokeinterface #624,  1          // InterfaceMethod java/util/List.size:()I
      61: istore_2
      62: iload_2
      63: ifne          75
      66: aload_0
      67: iconst_0
      68: invokevirtual #1385               // Method hideWhenNoProposals:(Z)Z
      71: ifeq          75
      74: return
      75: iload_2
      76: iconst_1
      77: if_icmpne     124
      80: aload_0
      81: aload_1
      82: iconst_0
      83: invokeinterface #626,  2          // InterfaceMethod java/util/List.get:(I)Ljava/lang/Object;
      88: checkcast     #629                // class org/eclipse/jface/text/contentassist/ICompletionProposal
      91: invokevirtual #1180               // Method canAutoInsert:(Lorg/eclipse/jface/text/contentassist/ICompletionProposal;)Z
      94: ifeq          124
      97: aload_0
      98: aload_1
      99: iconst_0
     100: invokeinterface #626,  2          // InterfaceMethod java/util/List.get:(I)Ljava/lang/Object;
     105: checkcast     #629                // class org/eclipse/jface/text/contentassist/ICompletionProposal
     108: iconst_0
     109: iconst_0
     110: aload_0
     111: getfield      #1123               // Field fInvocationOffset:I
     114: invokevirtual #764                // Method insertProposal:(Lorg/eclipse/jface/text/contentassist/ICompletionProposal;CII)V
     117: aload_0
     118: invokevirtual #201                // Method hide:()V
     121: goto          168
     124: aload_0
     125: invokevirtual #998                // Method ensureDocumentListenerInstalled:()V
     128: iload_2
     129: ifle          146
     132: aload_0
     133: invokevirtual #1174               // Method completeCommonPrefix:()Z
     136: ifeq          146
     139: aload_0
     140: invokevirtual #201                // Method hide:()V
     143: goto          168
     146: aload_0
     147: aload_1
     148: putfield      #211                // Field fComputedProposals:Ljava/util/List;
     151: aload_0
     152: invokevirtual #1387               // Method createProposalSelector:()V
     155: aload_0
     156: aload_0
     157: getfield      #211                // Field fComputedProposals:Ljava/util/List;
     160: iconst_0
     161: invokevirtual #213                // Method setProposals:(Ljava/util/List;Z)V
     164: aload_0
     165: invokevirtual #1389               // Method displayProposals:()V
     168: return
}
